{"datatypes":[{"tag":"DataDeclaration","fields":{"datatypeName":{"tyName":"Data"},"datatypeBinders":0,"datatypeConstructors":[{"constructorName":"Constr","constructorArgs":[{"tag":"BuiltinFlat","fields":[{"tag":"IntegerT"}]},{"tag":"Datatype","fields":[{"tyName":"List"},[{"tag":"Datatype","fields":[{"tyName":"Data"},[]]}]]}]},{"constructorName":"Map","constructorArgs":[{"tag":"Datatype","fields":[{"tyName":"List"},[{"tag":"Datatype","fields":[{"tyName":"Pair"},[{"tag":"Datatype","fields":[{"tyName":"Data"},[]]},{"tag":"Datatype","fields":[{"tyName":"Data"},[]]}]]}]]}]},{"constructorName":"List","constructorArgs":[{"tag":"Datatype","fields":[{"tyName":"List"},[{"tag":"Datatype","fields":[{"tyName":"Data"},[]]}]]}]},{"constructorName":"I","constructorArgs":[{"tag":"BuiltinFlat","fields":[{"tag":"IntegerT"}]}]},{"constructorName":"B","constructorArgs":[{"tag":"BuiltinFlat","fields":[{"tag":"ByteStringT"}]}]}],"datatypeEncoding":{"tag":"BuiltinStrategy","fields":[{"tag":"InternalDataStrat"}]}}},{"tag":"DataDeclaration","fields":{"datatypeName":{"tyName":"List"},"datatypeBinders":1,"datatypeConstructors":[{"constructorName":"Nil","constructorArgs":[]},{"constructorName":"Cons","constructorArgs":[{"tag":"Abstraction","fields":[[0,0]]},{"tag":"Datatype","fields":[{"tyName":"List"},[{"tag":"Abstraction","fields":[[0,0]]}]]}]}],"datatypeEncoding":{"tag":"BuiltinStrategy","fields":[{"tag":"InternalListStrat"}]}}},{"tag":"DataDeclaration","fields":{"datatypeName":{"tyName":"Map"},"datatypeBinders":2,"datatypeConstructors":[{"constructorName":"Map","constructorArgs":[{"tag":"Datatype","fields":[{"tyName":"List"},[{"tag":"Datatype","fields":[{"tyName":"Pair"},[{"tag":"Abstraction","fields":[[0,0]]},{"tag":"Abstraction","fields":[[0,1]]}]]}]]}]}],"datatypeEncoding":{"tag":"BuiltinStrategy","fields":[{"tag":"InternalAssocMapStrat"}]}}},{"tag":"DataDeclaration","fields":{"datatypeName":{"tyName":"Maybe"},"datatypeBinders":1,"datatypeConstructors":[{"constructorName":"Just","constructorArgs":[{"tag":"Abstraction","fields":[[0,0]]}]},{"constructorName":"Nothing","constructorArgs":[]}],"datatypeEncoding":{"tag":"PlutusData","fields":[{"tag":"ConstrData"}]}}},{"tag":"DataDeclaration","fields":{"datatypeName":{"tyName":"Pair"},"datatypeBinders":2,"datatypeConstructors":[{"constructorName":"Pair","constructorArgs":[{"tag":"Abstraction","fields":[[0,0]]},{"tag":"Abstraction","fields":[[0,1]]}]}],"datatypeEncoding":{"tag":"BuiltinStrategy","fields":[{"tag":"InternalPairStrat"}]}}}],"asg":[{"key":220,"value":{"tag":"ACompNode","fields":[[0,[{"tag":"Datatype","fields":[{"tyName":"Data"},[]]},{"tag":"BuiltinFlat","fields":[{"tag":"UnitT"}]}]],{"tag":"LamInternal","fields":[{"tag":"AnId","fields":[219]}]}]}},{"key":219,"value":{"tag":"AValNode","fields":[{"tag":"BuiltinFlat","fields":[{"tag":"UnitT"}]},{"tag":"App","fields":[218,[{"tag":"AnId","fields":[211]}],[],[0,[{"tag":"BuiltinFlat","fields":[{"tag":"UnitT"}]},{"tag":"BuiltinFlat","fields":[{"tag":"UnitT"}]}]]]}]}},{"key":218,"value":{"tag":"ACompNode","fields":[[0,[{"tag":"BuiltinFlat","fields":[{"tag":"UnitT"}]},{"tag":"BuiltinFlat","fields":[{"tag":"UnitT"}]}]],{"tag":"ForceInternal","fields":[{"tag":"AnId","fields":[217]}]}]}},{"key":217,"value":{"tag":"AValNode","fields":[{"tag":"ThunkT","fields":[[0,[{"tag":"BuiltinFlat","fields":[{"tag":"UnitT"}]},{"tag":"BuiltinFlat","fields":[{"tag":"UnitT"}]}]]]},{"tag":"App","fields":[44,[{"tag":"AnId","fields":[210]},{"tag":"AnId","fields":[213]},{"tag":"AnId","fields":[216]}],[{"tag":"Nowhere"}],[0,[{"tag":"BuiltinFlat","fields":[{"tag":"BoolT"}]},{"tag":"ThunkT","fields":[[0,[{"tag":"BuiltinFlat","fields":[{"tag":"UnitT"}]},{"tag":"BuiltinFlat","fields":[{"tag":"UnitT"}]}]]]},{"tag":"ThunkT","fields":[[0,[{"tag":"BuiltinFlat","fields":[{"tag":"UnitT"}]},{"tag":"BuiltinFlat","fields":[{"tag":"UnitT"}]}]]]},{"tag":"ThunkT","fields":[[0,[{"tag":"BuiltinFlat","fields":[{"tag":"UnitT"}]},{"tag":"BuiltinFlat","fields":[{"tag":"UnitT"}]}]]]}]]]}]}},{"key":216,"value":{"tag":"AValNode","fields":[{"tag":"ThunkT","fields":[[0,[{"tag":"BuiltinFlat","fields":[{"tag":"UnitT"}]},{"tag":"BuiltinFlat","fields":[{"tag":"UnitT"}]}]]]},{"tag":"Thunk","fields":[215]}]}},{"key":215,"value":{"tag":"ACompNode","fields":[[0,[{"tag":"BuiltinFlat","fields":[{"tag":"UnitT"}]},{"tag":"BuiltinFlat","fields":[{"tag":"UnitT"}]}]],{"tag":"LamInternal","fields":[{"tag":"AnId","fields":[214]}]}]}},{"key":214,"value":{"tag":"AnError"}},{"key":213,"value":{"tag":"AValNode","fields":[{"tag":"ThunkT","fields":[[0,[{"tag":"BuiltinFlat","fields":[{"tag":"UnitT"}]},{"tag":"BuiltinFlat","fields":[{"tag":"UnitT"}]}]]]},{"tag":"Thunk","fields":[212]}]}},{"key":212,"value":{"tag":"ACompNode","fields":[[0,[{"tag":"BuiltinFlat","fields":[{"tag":"UnitT"}]},{"tag":"BuiltinFlat","fields":[{"tag":"UnitT"}]}]],{"tag":"LamInternal","fields":[{"tag":"AnId","fields":[211]}]}]}},{"key":211,"value":{"tag":"AValNode","fields":[{"tag":"BuiltinFlat","fields":[{"tag":"UnitT"}]},{"tag":"Lit","fields":[{"tag":"AUnit"}]}]}},{"key":210,"value":{"tag":"AValNode","fields":[{"tag":"BuiltinFlat","fields":[{"tag":"BoolT"}]},{"tag":"App","fields":[209,[{"tag":"AnId","fields":[208]},{"tag":"AnId","fields":[170]}],[],[0,[{"tag":"BuiltinFlat","fields":[{"tag":"IntegerT"}]},{"tag":"BuiltinFlat","fields":[{"tag":"IntegerT"}]},{"tag":"BuiltinFlat","fields":[{"tag":"BoolT"}]}]]]}]}},{"key":209,"value":{"tag":"ACompNode","fields":[[0,[{"tag":"BuiltinFlat","fields":[{"tag":"IntegerT"}]},{"tag":"BuiltinFlat","fields":[{"tag":"IntegerT"}]},{"tag":"BuiltinFlat","fields":[{"tag":"BoolT"}]}]],{"tag":"Builtin2Internal","fields":[{"tag":"EqualsInteger"}]}]}},{"key":208,"value":{"tag":"AValNode","fields":[{"tag":"BuiltinFlat","fields":[{"tag":"IntegerT"}]},{"tag":"App","fields":[166,[{"tag":"AnId","fields":[207]}],[],[0,[{"tag":"Datatype","fields":[{"tyName":"Data"},[]]},{"tag":"BuiltinFlat","fields":[{"tag":"IntegerT"}]}]]]}]}},{"key":207,"value":{"tag":"AValNode","fields":[{"tag":"Datatype","fields":[{"tyName":"Data"},[]]},{"tag":"App","fields":[206,[{"tag":"AnId","fields":[42]}],[],[0,[{"tag":"Datatype","fields":[{"tyName":"Data"},[]]},{"tag":"Datatype","fields":[{"tyName":"Data"},[]]}]]]}]}},{"key":206,"value":{"tag":"ACompNode","fields":[[0,[{"tag":"Datatype","fields":[{"tyName":"Data"},[]]},{"tag":"Datatype","fields":[{"tyName":"Data"},[]]}]],{"tag":"ForceInternal","fields":[{"tag":"AnId","fields":[205]}]}]}},{"key":205,"value":{"tag":"AValNode","fields":[{"tag":"ThunkT","fields":[[0,[{"tag":"Datatype","fields":[{"tyName":"Data"},[]]},{"tag":"Datatype","fields":[{"tyName":"Data"},[]]}]]]},{"tag":"App","fields":[44,[{"tag":"AnId","fields":[50]},{"tag":"AnId","fields":[54]},{"tag":"AnId","fields":[204]}],[{"tag":"Nowhere"}],[0,[{"tag":"BuiltinFlat","fields":[{"tag":"BoolT"}]},{"tag":"ThunkT","fields":[[0,[{"tag":"Datatype","fields":[{"tyName":"Data"},[]]},{"tag":"Datatype","fields":[{"tyName":"Data"},[]]}]]]},{"tag":"ThunkT","fields":[[0,[{"tag":"Datatype","fields":[{"tyName":"Data"},[]]},{"tag":"Datatype","fields":[{"tyName":"Data"},[]]}]]]},{"tag":"ThunkT","fields":[[0,[{"tag":"Datatype","fields":[{"tyName":"Data"},[]]},{"tag":"Datatype","fields":[{"tyName":"Data"},[]]}]]]}]]]}]}},{"key":204,"value":{"tag":"AValNode","fields":[{"tag":"ThunkT","fields":[[0,[{"tag":"Datatype","fields":[{"tyName":"Data"},[]]},{"tag":"Datatype","fields":[{"tyName":"Data"},[]]}]]]},{"tag":"Thunk","fields":[203]}]}},{"key":203,"value":{"tag":"ACompNode","fields":[[0,[{"tag":"Datatype","fields":[{"tyName":"Data"},[]]},{"tag":"Datatype","fields":[{"tyName":"Data"},[]]}]],{"tag":"LamInternal","fields":[{"tag":"AnId","fields":[202]}]}]}},{"key":202,"value":{"tag":"AValNode","fields":[{"tag":"Datatype","fields":[{"tyName":"Data"},[]]},{"tag":"App","fields":[44,[{"tag":"AnId","fields":[169]},{"tag":"AnId","fields":[171]},{"tag":"AnId","fields":[201]}],[{"tag":"Nowhere"}],[0,[{"tag":"BuiltinFlat","fields":[{"tag":"BoolT"}]},{"tag":"Datatype","fields":[{"tyName":"Data"},[]]},{"tag":"Datatype","fields":[{"tyName":"Data"},[]]},{"tag":"Datatype","fields":[{"tyName":"Data"},[]]}]]]}]}},{"key":201,"value":{"tag":"AValNode","fields":[{"tag":"Datatype","fields":[{"tyName":"Data"},[]]},{"tag":"App","fields":[200,[{"tag":"AnId","fields":[62]}],[],[0,[{"tag":"Datatype","fields":[{"tyName":"Data"},[]]},{"tag":"Datatype","fields":[{"tyName":"Data"},[]]}]]]}]}},{"key":200,"value":{"tag":"ACompNode","fields":[[0,[{"tag":"Datatype","fields":[{"tyName":"Data"},[]]},{"tag":"Datatype","fields":[{"tyName":"Data"},[]]}]],{"tag":"ForceInternal","fields":[{"tag":"AnId","fields":[199]}]}]}},{"key":199,"value":{"tag":"AValNode","fields":[{"tag":"ThunkT","fields":[[0,[{"tag":"Datatype","fields":[{"tyName":"Data"},[]]},{"tag":"Datatype","fields":[{"tyName":"Data"},[]]}]]]},{"tag":"App","fields":[44,[{"tag":"AnId","fields":[177]},{"tag":"AnId","fields":[54]},{"tag":"AnId","fields":[198]}],[{"tag":"Nowhere"}],[0,[{"tag":"BuiltinFlat","fields":[{"tag":"BoolT"}]},{"tag":"ThunkT","fields":[[0,[{"tag":"Datatype","fields":[{"tyName":"Data"},[]]},{"tag":"Datatype","fields":[{"tyName":"Data"},[]]}]]]},{"tag":"ThunkT","fields":[[0,[{"tag":"Datatype","fields":[{"tyName":"Data"},[]]},{"tag":"Datatype","fields":[{"tyName":"Data"},[]]}]]]},{"tag":"ThunkT","fields":[[0,[{"tag":"Datatype","fields":[{"tyName":"Data"},[]]},{"tag":"Datatype","fields":[{"tyName":"Data"},[]]}]]]}]]]}]}},{"key":198,"value":{"tag":"AValNode","fields":[{"tag":"ThunkT","fields":[[0,[{"tag":"Datatype","fields":[{"tyName":"Data"},[]]},{"tag":"Datatype","fields":[{"tyName":"Data"},[]]}]]]},{"tag":"Thunk","fields":[197]}]}},{"key":197,"value":{"tag":"ACompNode","fields":[[0,[{"tag":"Datatype","fields":[{"tyName":"Data"},[]]},{"tag":"Datatype","fields":[{"tyName":"Data"},[]]}]],{"tag":"LamInternal","fields":[{"tag":"AnId","fields":[196]}]}]}},{"key":196,"value":{"tag":"AValNode","fields":[{"tag":"Datatype","fields":[{"tyName":"Data"},[]]},{"tag":"App","fields":[44,[{"tag":"AnId","fields":[169]},{"tag":"AnId","fields":[171]},{"tag":"AnId","fields":[195]}],[{"tag":"Nowhere"}],[0,[{"tag":"BuiltinFlat","fields":[{"tag":"BoolT"}]},{"tag":"Datatype","fields":[{"tyName":"Data"},[]]},{"tag":"Datatype","fields":[{"tyName":"Data"},[]]},{"tag":"Datatype","fields":[{"tyName":"Data"},[]]}]]]}]}},{"key":195,"value":{"tag":"AValNode","fields":[{"tag":"Datatype","fields":[{"tyName":"Data"},[]]},{"tag":"App","fields":[194,[{"tag":"AnId","fields":[62]}],[],[0,[{"tag":"Datatype","fields":[{"tyName":"Data"},[]]},{"tag":"Datatype","fields":[{"tyName":"Data"},[]]}]]]}]}},{"key":194,"value":{"tag":"ACompNode","fields":[[0,[{"tag":"Datatype","fields":[{"tyName":"Data"},[]]},{"tag":"Datatype","fields":[{"tyName":"Data"},[]]}]],{"tag":"ForceInternal","fields":[{"tag":"AnId","fields":[193]}]}]}},{"key":193,"value":{"tag":"AValNode","fields":[{"tag":"ThunkT","fields":[[0,[{"tag":"Datatype","fields":[{"tyName":"Data"},[]]},{"tag":"Datatype","fields":[{"tyName":"Data"},[]]}]]]},{"tag":"App","fields":[44,[{"tag":"AnId","fields":[177]},{"tag":"AnId","fields":[54]},{"tag":"AnId","fields":[192]}],[{"tag":"Nowhere"}],[0,[{"tag":"BuiltinFlat","fields":[{"tag":"BoolT"}]},{"tag":"ThunkT","fields":[[0,[{"tag":"Datatype","fields":[{"tyName":"Data"},[]]},{"tag":"Datatype","fields":[{"tyName":"Data"},[]]}]]]},{"tag":"ThunkT","fields":[[0,[{"tag":"Datatype","fields":[{"tyName":"Data"},[]]},{"tag":"Datatype","fields":[{"tyName":"Data"},[]]}]]]},{"tag":"ThunkT","fields":[[0,[{"tag":"Datatype","fields":[{"tyName":"Data"},[]]},{"tag":"Datatype","fields":[{"tyName":"Data"},[]]}]]]}]]]}]}},{"key":192,"value":{"tag":"AValNode","fields":[{"tag":"ThunkT","fields":[[0,[{"tag":"Datatype","fields":[{"tyName":"Data"},[]]},{"tag":"Datatype","fields":[{"tyName":"Data"},[]]}]]]},{"tag":"Thunk","fields":[191]}]}},{"key":191,"value":{"tag":"ACompNode","fields":[[0,[{"tag":"Datatype","fields":[{"tyName":"Data"},[]]},{"tag":"Datatype","fields":[{"tyName":"Data"},[]]}]],{"tag":"LamInternal","fields":[{"tag":"AnId","fields":[190]}]}]}},{"key":190,"value":{"tag":"AValNode","fields":[{"tag":"Datatype","fields":[{"tyName":"Data"},[]]},{"tag":"App","fields":[44,[{"tag":"AnId","fields":[169]},{"tag":"AnId","fields":[171]},{"tag":"AnId","fields":[189]}],[{"tag":"Nowhere"}],[0,[{"tag":"BuiltinFlat","fields":[{"tag":"BoolT"}]},{"tag":"Datatype","fields":[{"tyName":"Data"},[]]},{"tag":"Datatype","fields":[{"tyName":"Data"},[]]},{"tag":"Datatype","fields":[{"tyName":"Data"},[]]}]]]}]}},{"key":189,"value":{"tag":"AValNode","fields":[{"tag":"Datatype","fields":[{"tyName":"Data"},[]]},{"tag":"App","fields":[188,[{"tag":"AnId","fields":[62]}],[],[0,[{"tag":"Datatype","fields":[{"tyName":"Data"},[]]},{"tag":"Datatype","fields":[{"tyName":"Data"},[]]}]]]}]}},{"key":188,"value":{"tag":"ACompNode","fields":[[0,[{"tag":"Datatype","fields":[{"tyName":"Data"},[]]},{"tag":"Datatype","fields":[{"tyName":"Data"},[]]}]],{"tag":"ForceInternal","fields":[{"tag":"AnId","fields":[187]}]}]}},{"key":187,"value":{"tag":"AValNode","fields":[{"tag":"ThunkT","fields":[[0,[{"tag":"Datatype","fields":[{"tyName":"Data"},[]]},{"tag":"Datatype","fields":[{"tyName":"Data"},[]]}]]]},{"tag":"App","fields":[44,[{"tag":"AnId","fields":[177]},{"tag":"AnId","fields":[54]},{"tag":"AnId","fields":[186]}],[{"tag":"Nowhere"}],[0,[{"tag":"BuiltinFlat","fields":[{"tag":"BoolT"}]},{"tag":"ThunkT","fields":[[0,[{"tag":"Datatype","fields":[{"tyName":"Data"},[]]},{"tag":"Datatype","fields":[{"tyName":"Data"},[]]}]]]},{"tag":"ThunkT","fields":[[0,[{"tag":"Datatype","fields":[{"tyName":"Data"},[]]},{"tag":"Datatype","fields":[{"tyName":"Data"},[]]}]]]},{"tag":"ThunkT","fields":[[0,[{"tag":"Datatype","fields":[{"tyName":"Data"},[]]},{"tag":"Datatype","fields":[{"tyName":"Data"},[]]}]]]}]]]}]}},{"key":186,"value":{"tag":"AValNode","fields":[{"tag":"ThunkT","fields":[[0,[{"tag":"Datatype","fields":[{"tyName":"Data"},[]]},{"tag":"Datatype","fields":[{"tyName":"Data"},[]]}]]]},{"tag":"Thunk","fields":[185]}]}},{"key":185,"value":{"tag":"ACompNode","fields":[[0,[{"tag":"Datatype","fields":[{"tyName":"Data"},[]]},{"tag":"Datatype","fields":[{"tyName":"Data"},[]]}]],{"tag":"LamInternal","fields":[{"tag":"AnId","fields":[184]}]}]}},{"key":184,"value":{"tag":"AValNode","fields":[{"tag":"Datatype","fields":[{"tyName":"Data"},[]]},{"tag":"App","fields":[44,[{"tag":"AnId","fields":[169]},{"tag":"AnId","fields":[171]},{"tag":"AnId","fields":[183]}],[{"tag":"Nowhere"}],[0,[{"tag":"BuiltinFlat","fields":[{"tag":"BoolT"}]},{"tag":"Datatype","fields":[{"tyName":"Data"},[]]},{"tag":"Datatype","fields":[{"tyName":"Data"},[]]},{"tag":"Datatype","fields":[{"tyName":"Data"},[]]}]]]}]}},{"key":183,"value":{"tag":"AValNode","fields":[{"tag":"Datatype","fields":[{"tyName":"Data"},[]]},{"tag":"App","fields":[182,[{"tag":"AnId","fields":[62]}],[],[0,[{"tag":"Datatype","fields":[{"tyName":"Data"},[]]},{"tag":"Datatype","fields":[{"tyName":"Data"},[]]}]]]}]}},{"key":182,"value":{"tag":"ACompNode","fields":[[0,[{"tag":"Datatype","fields":[{"tyName":"Data"},[]]},{"tag":"Datatype","fields":[{"tyName":"Data"},[]]}]],{"tag":"ForceInternal","fields":[{"tag":"AnId","fields":[181]}]}]}},{"key":181,"value":{"tag":"AValNode","fields":[{"tag":"ThunkT","fields":[[0,[{"tag":"Datatype","fields":[{"tyName":"Data"},[]]},{"tag":"Datatype","fields":[{"tyName":"Data"},[]]}]]]},{"tag":"App","fields":[44,[{"tag":"AnId","fields":[177]},{"tag":"AnId","fields":[54]},{"tag":"AnId","fields":[180]}],[{"tag":"Nowhere"}],[0,[{"tag":"BuiltinFlat","fields":[{"tag":"BoolT"}]},{"tag":"ThunkT","fields":[[0,[{"tag":"Datatype","fields":[{"tyName":"Data"},[]]},{"tag":"Datatype","fields":[{"tyName":"Data"},[]]}]]]},{"tag":"ThunkT","fields":[[0,[{"tag":"Datatype","fields":[{"tyName":"Data"},[]]},{"tag":"Datatype","fields":[{"tyName":"Data"},[]]}]]]},{"tag":"ThunkT","fields":[[0,[{"tag":"Datatype","fields":[{"tyName":"Data"},[]]},{"tag":"Datatype","fields":[{"tyName":"Data"},[]]}]]]}]]]}]}},{"key":180,"value":{"tag":"AValNode","fields":[{"tag":"ThunkT","fields":[[0,[{"tag":"Datatype","fields":[{"tyName":"Data"},[]]},{"tag":"Datatype","fields":[{"tyName":"Data"},[]]}]]]},{"tag":"Thunk","fields":[179]}]}},{"key":179,"value":{"tag":"ACompNode","fields":[[0,[{"tag":"Datatype","fields":[{"tyName":"Data"},[]]},{"tag":"Datatype","fields":[{"tyName":"Data"},[]]}]],{"tag":"LamInternal","fields":[{"tag":"AnId","fields":[178]}]}]}},{"key":178,"value":{"tag":"AValNode","fields":[{"tag":"Datatype","fields":[{"tyName":"Data"},[]]},{"tag":"App","fields":[44,[{"tag":"AnId","fields":[169]},{"tag":"AnId","fields":[171]},{"tag":"AnId","fields":[52]}],[{"tag":"Nowhere"}],[0,[{"tag":"BuiltinFlat","fields":[{"tag":"BoolT"}]},{"tag":"Datatype","fields":[{"tyName":"Data"},[]]},{"tag":"Datatype","fields":[{"tyName":"Data"},[]]},{"tag":"Datatype","fields":[{"tyName":"Data"},[]]}]]]}]}},{"key":177,"value":{"tag":"AValNode","fields":[{"tag":"BuiltinFlat","fields":[{"tag":"BoolT"}]},{"tag":"App","fields":[43,[{"tag":"AnId","fields":[176]}],[{"tag":"Nowhere"}],[0,[{"tag":"Datatype","fields":[{"tyName":"List"},[{"tag":"Datatype","fields":[{"tyName":"Data"},[]]}]]},{"tag":"BuiltinFlat","fields":[{"tag":"BoolT"}]}]]]}]}},{"key":176,"value":{"tag":"AValNode","fields":[{"tag":"Datatype","fields":[{"tyName":"List"},[{"tag":"Datatype","fields":[{"tyName":"Data"},[]]}]]},{"tag":"App","fields":[36,[{"tag":"AnId","fields":[175]}],[],[0,[{"tag":"Datatype","fields":[{"tyName":"Data"},[]]},{"tag":"Datatype","fields":[{"tyName":"List"},[{"tag":"Datatype","fields":[{"tyName":"Data"},[]]}]]}]]]}]}},{"key":175,"value":{"tag":"AValNode","fields":[{"tag":"Datatype","fields":[{"tyName":"Data"},[]]},{"tag":"App","fields":[7,[{"tag":"AnId","fields":[174]}],[{"tag":"Nowhere"}],[0,[{"tag":"Datatype","fields":[{"tyName":"List"},[{"tag":"Datatype","fields":[{"tyName":"Data"},[]]}]]},{"tag":"Datatype","fields":[{"tyName":"Data"},[]]}]]]}]}},{"key":174,"value":{"tag":"AValNode","fields":[{"tag":"Datatype","fields":[{"tyName":"List"},[{"tag":"Datatype","fields":[{"tyName":"Data"},[]]}]]},{"tag":"App","fields":[4,[{"tag":"AnId","fields":[173]}],[{"tag":"Nowhere"}],[0,[{"tag":"Datatype","fields":[{"tyName":"List"},[{"tag":"Datatype","fields":[{"tyName":"Data"},[]]}]]},{"tag":"Datatype","fields":[{"tyName":"List"},[{"tag":"Datatype","fields":[{"tyName":"Data"},[]]}]]}]]]}]}},{"key":173,"value":{"tag":"AValNode","fields":[{"tag":"Datatype","fields":[{"tyName":"List"},[{"tag":"Datatype","fields":[{"tyName":"Data"},[]]}]]},{"tag":"App","fields":[2,[{"tag":"AnId","fields":[172]}],[{"tag":"Nowhere"},{"tag":"Nowhere"}],[0,[{"tag":"Datatype","fields":[{"tyName":"Pair"},[{"tag":"BuiltinFlat","fields":[{"tag":"IntegerT"}]},{"tag":"Datatype","fields":[{"tyName":"List"},[{"tag":"Datatype","fields":[{"tyName":"Data"},[]]}]]}]]},{"tag":"Datatype","fields":[{"tyName":"List"},[{"tag":"Datatype","fields":[{"tyName":"Data"},[]]}]]}]]]}]}},{"key":172,"value":{"tag":"AValNode","fields":[{"tag":"Datatype","fields":[{"tyName":"Pair"},[{"tag":"BuiltinFlat","fields":[{"tag":"IntegerT"}]},{"tag":"Datatype","fields":[{"tyName":"List"},[{"tag":"Datatype","fields":[{"tyName":"Data"},[]]}]]}]]},{"tag":"App","fields":[0,[{"tag":"AnId","fields":[62]}],[],[0,[{"tag":"Datatype","fields":[{"tyName":"Data"},[]]},{"tag":"Datatype","fields":[{"tyName":"Pair"},[{"tag":"BuiltinFlat","fields":[{"tag":"IntegerT"}]},{"tag":"Datatype","fields":[{"tyName":"List"},[{"tag":"Datatype","fields":[{"tyName":"Data"},[]]}]]}]]}]]]}]}},{"key":171,"value":{"tag":"AValNode","fields":[{"tag":"Datatype","fields":[{"tyName":"Data"},[]]},{"tag":"App","fields":[51,[{"tag":"AnId","fields":[170]}],[],[0,[{"tag":"BuiltinFlat","fields":[{"tag":"IntegerT"}]},{"tag":"Datatype","fields":[{"tyName":"Data"},[]]}]]]}]}},{"key":170,"value":{"tag":"AValNode","fields":[{"tag":"BuiltinFlat","fields":[{"tag":"IntegerT"}]},{"tag":"Lit","fields":[{"tag":"AnInteger","fields":[1]}]}]}},{"key":169,"value":{"tag":"AValNode","fields":[{"tag":"BuiltinFlat","fields":[{"tag":"BoolT"}]},{"tag":"App","fields":[168,[{"tag":"AnId","fields":[21]},{"tag":"AnId","fields":[167]}],[],[0,[{"tag":"BuiltinFlat","fields":[{"tag":"IntegerT"}]},{"tag":"BuiltinFlat","fields":[{"tag":"IntegerT"}]},{"tag":"BuiltinFlat","fields":[{"tag":"BoolT"}]}]]]}]}},{"key":168,"value":{"tag":"ACompNode","fields":[[0,[{"tag":"BuiltinFlat","fields":[{"tag":"IntegerT"}]},{"tag":"BuiltinFlat","fields":[{"tag":"IntegerT"}]},{"tag":"BuiltinFlat","fields":[{"tag":"BoolT"}]}]],{"tag":"Builtin2Internal","fields":[{"tag":"LessThanInteger"}]}]}},{"key":167,"value":{"tag":"AValNode","fields":[{"tag":"BuiltinFlat","fields":[{"tag":"IntegerT"}]},{"tag":"App","fields":[166,[{"tag":"AnId","fields":[165]}],[],[0,[{"tag":"Datatype","fields":[{"tyName":"Data"},[]]},{"tag":"BuiltinFlat","fields":[{"tag":"IntegerT"}]}]]]}]}},{"key":166,"value":{"tag":"ACompNode","fields":[[0,[{"tag":"Datatype","fields":[{"tyName":"Data"},[]]},{"tag":"BuiltinFlat","fields":[{"tag":"IntegerT"}]}]],{"tag":"Builtin1Internal","fields":[{"tag":"UnIData"}]}]}},{"key":165,"value":{"tag":"AValNode","fields":[{"tag":"Datatype","fields":[{"tyName":"Data"},[]]},{"tag":"App","fields":[164,[{"tag":"AnId","fields":[159]}],[],[0,[{"tag":"Datatype","fields":[{"tyName":"Data"},[]]},{"tag":"Datatype","fields":[{"tyName":"Data"},[]]}]]]}]}},{"key":164,"value":{"tag":"ACompNode","fields":[[0,[{"tag":"Datatype","fields":[{"tyName":"Data"},[]]},{"tag":"Datatype","fields":[{"tyName":"Data"},[]]}]],{"tag":"ForceInternal","fields":[{"tag":"AnId","fields":[163]}]}]}},{"key":163,"value":{"tag":"AValNode","fields":[{"tag":"ThunkT","fields":[[0,[{"tag":"Datatype","fields":[{"tyName":"Data"},[]]},{"tag":"Datatype","fields":[{"tyName":"Data"},[]]}]]]},{"tag":"App","fields":[44,[{"tag":"AnId","fields":[162]},{"tag":"AnId","fields":[54]},{"tag":"AnId","fields":[152]}],[{"tag":"Nowhere"}],[0,[{"tag":"BuiltinFlat","fields":[{"tag":"BoolT"}]},{"tag":"ThunkT","fields":[[0,[{"tag":"Datatype","fields":[{"tyName":"Data"},[]]},{"tag":"Datatype","fields":[{"tyName":"Data"},[]]}]]]},{"tag":"ThunkT","fields":[[0,[{"tag":"Datatype","fields":[{"tyName":"Data"},[]]},{"tag":"Datatype","fields":[{"tyName":"Data"},[]]}]]]},{"tag":"ThunkT","fields":[[0,[{"tag":"Datatype","fields":[{"tyName":"Data"},[]]},{"tag":"Datatype","fields":[{"tyName":"Data"},[]]}]]]}]]]}]}},{"key":162,"value":{"tag":"AValNode","fields":[{"tag":"BuiltinFlat","fields":[{"tag":"BoolT"}]},{"tag":"App","fields":[43,[{"tag":"AnId","fields":[161]}],[{"tag":"Nowhere"}],[0,[{"tag":"Datatype","fields":[{"tyName":"List"},[{"tag":"Datatype","fields":[{"tyName":"Pair"},[{"tag":"Datatype","fields":[{"tyName":"Data"},[]]},{"tag":"Datatype","fields":[{"tyName":"Data"},[]]}]]}]]},{"tag":"BuiltinFlat","fields":[{"tag":"BoolT"}]}]]]}]}},{"key":161,"value":{"tag":"AValNode","fields":[{"tag":"Datatype","fields":[{"tyName":"List"},[{"tag":"Datatype","fields":[{"tyName":"Pair"},[{"tag":"Datatype","fields":[{"tyName":"Data"},[]]},{"tag":"Datatype","fields":[{"tyName":"Data"},[]]}]]}]]},{"tag":"App","fields":[4,[{"tag":"AnId","fields":[160]}],[{"tag":"Nowhere"}],[0,[{"tag":"Datatype","fields":[{"tyName":"List"},[{"tag":"Datatype","fields":[{"tyName":"Pair"},[{"tag":"Datatype","fields":[{"tyName":"Data"},[]]},{"tag":"Datatype","fields":[{"tyName":"Data"},[]]}]]}]]},{"tag":"Datatype","fields":[{"tyName":"List"},[{"tag":"Datatype","fields":[{"tyName":"Pair"},[{"tag":"Datatype","fields":[{"tyName":"Data"},[]]},{"tag":"Datatype","fields":[{"tyName":"Data"},[]]}]]}]]}]]]}]}},{"key":160,"value":{"tag":"AValNode","fields":[{"tag":"Datatype","fields":[{"tyName":"List"},[{"tag":"Datatype","fields":[{"tyName":"Pair"},[{"tag":"Datatype","fields":[{"tyName":"Data"},[]]},{"tag":"Datatype","fields":[{"tyName":"Data"},[]]}]]}]]},{"tag":"App","fields":[69,[{"tag":"AnId","fields":[159]}],[],[0,[{"tag":"Datatype","fields":[{"tyName":"Data"},[]]},{"tag":"Datatype","fields":[{"tyName":"List"},[{"tag":"Datatype","fields":[{"tyName":"Pair"},[{"tag":"Datatype","fields":[{"tyName":"Data"},[]]},{"tag":"Datatype","fields":[{"tyName":"Data"},[]]}]]}]]}]]]}]}},{"key":159,"value":{"tag":"AValNode","fields":[{"tag":"Datatype","fields":[{"tyName":"Data"},[]]},{"tag":"App","fields":[74,[{"tag":"AnId","fields":[158]}],[],[0,[{"tag":"Datatype","fields":[{"tyName":"List"},[{"tag":"Datatype","fields":[{"tyName":"Pair"},[{"tag":"Datatype","fields":[{"tyName":"Data"},[]]},{"tag":"Datatype","fields":[{"tyName":"Data"},[]]}]]}]]},{"tag":"Datatype","fields":[{"tyName":"Data"},[]]}]]]}]}},{"key":158,"value":{"tag":"AValNode","fields":[{"tag":"Datatype","fields":[{"tyName":"List"},[{"tag":"Datatype","fields":[{"tyName":"Pair"},[{"tag":"Datatype","fields":[{"tyName":"Data"},[]]},{"tag":"Datatype","fields":[{"tyName":"Data"},[]]}]]}]]},{"tag":"App","fields":[25,[{"tag":"AnId","fields":[157]},{"tag":"AnId","fields":[156]}],[{"tag":"Nowhere"}],[0,[{"tag":"Datatype","fields":[{"tyName":"Pair"},[{"tag":"Datatype","fields":[{"tyName":"Data"},[]]},{"tag":"Datatype","fields":[{"tyName":"Data"},[]]}]]},{"tag":"Datatype","fields":[{"tyName":"List"},[{"tag":"Datatype","fields":[{"tyName":"Pair"},[{"tag":"Datatype","fields":[{"tyName":"Data"},[]]},{"tag":"Datatype","fields":[{"tyName":"Data"},[]]}]]}]]},{"tag":"Datatype","fields":[{"tyName":"List"},[{"tag":"Datatype","fields":[{"tyName":"Pair"},[{"tag":"Datatype","fields":[{"tyName":"Data"},[]]},{"tag":"Datatype","fields":[{"tyName":"Data"},[]]}]]}]]}]]]}]}},{"key":157,"value":{"tag":"AValNode","fields":[{"tag":"Datatype","fields":[{"tyName":"Pair"},[{"tag":"Datatype","fields":[{"tyName":"Data"},[]]},{"tag":"Datatype","fields":[{"tyName":"Data"},[]]}]]},{"tag":"App","fields":[71,[{"tag":"AnId","fields":[64]},{"tag":"AnId","fields":[64]}],[],[0,[{"tag":"Datatype","fields":[{"tyName":"Data"},[]]},{"tag":"Datatype","fields":[{"tyName":"Data"},[]]},{"tag":"Datatype","fields":[{"tyName":"Pair"},[{"tag":"Datatype","fields":[{"tyName":"Data"},[]]},{"tag":"Datatype","fields":[{"tyName":"Data"},[]]}]]}]]]}]}},{"key":156,"value":{"tag":"AValNode","fields":[{"tag":"Datatype","fields":[{"tyName":"List"},[{"tag":"Datatype","fields":[{"tyName":"Pair"},[{"tag":"Datatype","fields":[{"tyName":"Data"},[]]},{"tag":"Datatype","fields":[{"tyName":"Data"},[]]}]]}]]},{"tag":"App","fields":[69,[{"tag":"AnId","fields":[155]}],[],[0,[{"tag":"Datatype","fields":[{"tyName":"Data"},[]]},{"tag":"Datatype","fields":[{"tyName":"List"},[{"tag":"Datatype","fields":[{"tyName":"Pair"},[{"tag":"Datatype","fields":[{"tyName":"Data"},[]]},{"tag":"Datatype","fields":[{"tyName":"Data"},[]]}]]}]]}]]]}]}},{"key":155,"value":{"tag":"AValNode","fields":[{"tag":"Datatype","fields":[{"tyName":"Data"},[]]},{"tag":"App","fields":[154,[{"tag":"AnId","fields":[75]}],[],[0,[{"tag":"Datatype","fields":[{"tyName":"Data"},[]]},{"tag":"Datatype","fields":[{"tyName":"Data"},[]]}]]]}]}},{"key":154,"value":{"tag":"ACompNode","fields":[[0,[{"tag":"Datatype","fields":[{"tyName":"Data"},[]]},{"tag":"Datatype","fields":[{"tyName":"Data"},[]]}]],{"tag":"ForceInternal","fields":[{"tag":"AnId","fields":[153]}]}]}},{"key":153,"value":{"tag":"AValNode","fields":[{"tag":"ThunkT","fields":[[0,[{"tag":"Datatype","fields":[{"tyName":"Data"},[]]},{"tag":"Datatype","fields":[{"tyName":"Data"},[]]}]]]},{"tag":"App","fields":[44,[{"tag":"AnId","fields":[79]},{"tag":"AnId","fields":[54]},{"tag":"AnId","fields":[152]}],[{"tag":"Nowhere"}],[0,[{"tag":"BuiltinFlat","fields":[{"tag":"BoolT"}]},{"tag":"ThunkT","fields":[[0,[{"tag":"Datatype","fields":[{"tyName":"Data"},[]]},{"tag":"Datatype","fields":[{"tyName":"Data"},[]]}]]]},{"tag":"ThunkT","fields":[[0,[{"tag":"Datatype","fields":[{"tyName":"Data"},[]]},{"tag":"Datatype","fields":[{"tyName":"Data"},[]]}]]]},{"tag":"ThunkT","fields":[[0,[{"tag":"Datatype","fields":[{"tyName":"Data"},[]]},{"tag":"Datatype","fields":[{"tyName":"Data"},[]]}]]]}]]]}]}},{"key":152,"value":{"tag":"AValNode","fields":[{"tag":"ThunkT","fields":[[0,[{"tag":"Datatype","fields":[{"tyName":"Data"},[]]},{"tag":"Datatype","fields":[{"tyName":"Data"},[]]}]]]},{"tag":"Thunk","fields":[151]}]}},{"key":151,"value":{"tag":"ACompNode","fields":[[0,[{"tag":"Datatype","fields":[{"tyName":"Data"},[]]},{"tag":"Datatype","fields":[{"tyName":"Data"},[]]}]],{"tag":"LamInternal","fields":[{"tag":"AnId","fields":[150]}]}]}},{"key":150,"value":{"tag":"AValNode","fields":[{"tag":"Datatype","fields":[{"tyName":"Data"},[]]},{"tag":"App","fields":[44,[{"tag":"AnId","fields":[92]},{"tag":"AnId","fields":[90]},{"tag":"AnId","fields":[149]}],[{"tag":"Nowhere"}],[0,[{"tag":"BuiltinFlat","fields":[{"tag":"BoolT"}]},{"tag":"Datatype","fields":[{"tyName":"Data"},[]]},{"tag":"Datatype","fields":[{"tyName":"Data"},[]]},{"tag":"Datatype","fields":[{"tyName":"Data"},[]]}]]]}]}},{"key":149,"value":{"tag":"AValNode","fields":[{"tag":"Datatype","fields":[{"tyName":"Data"},[]]},{"tag":"App","fields":[148,[{"tag":"AnId","fields":[88]}],[],[0,[{"tag":"Datatype","fields":[{"tyName":"Data"},[]]},{"tag":"Datatype","fields":[{"tyName":"Data"},[]]}]]]}]}},{"key":148,"value":{"tag":"ACompNode","fields":[[0,[{"tag":"Datatype","fields":[{"tyName":"Data"},[]]},{"tag":"Datatype","fields":[{"tyName":"Data"},[]]}]],{"tag":"ForceInternal","fields":[{"tag":"AnId","fields":[147]}]}]}},{"key":147,"value":{"tag":"AValNode","fields":[{"tag":"ThunkT","fields":[[0,[{"tag":"Datatype","fields":[{"tyName":"Data"},[]]},{"tag":"Datatype","fields":[{"tyName":"Data"},[]]}]]]},{"tag":"App","fields":[44,[{"tag":"AnId","fields":[95]},{"tag":"AnId","fields":[54]},{"tag":"AnId","fields":[146]}],[{"tag":"Nowhere"}],[0,[{"tag":"BuiltinFlat","fields":[{"tag":"BoolT"}]},{"tag":"ThunkT","fields":[[0,[{"tag":"Datatype","fields":[{"tyName":"Data"},[]]},{"tag":"Datatype","fields":[{"tyName":"Data"},[]]}]]]},{"tag":"ThunkT","fields":[[0,[{"tag":"Datatype","fields":[{"tyName":"Data"},[]]},{"tag":"Datatype","fields":[{"tyName":"Data"},[]]}]]]},{"tag":"ThunkT","fields":[[0,[{"tag":"Datatype","fields":[{"tyName":"Data"},[]]},{"tag":"Datatype","fields":[{"tyName":"Data"},[]]}]]]}]]]}]}},{"key":146,"value":{"tag":"AValNode","fields":[{"tag":"ThunkT","fields":[[0,[{"tag":"Datatype","fields":[{"tyName":"Data"},[]]},{"tag":"Datatype","fields":[{"tyName":"Data"},[]]}]]]},{"tag":"Thunk","fields":[145]}]}},{"key":145,"value":{"tag":"ACompNode","fields":[[0,[{"tag":"Datatype","fields":[{"tyName":"Data"},[]]},{"tag":"Datatype","fields":[{"tyName":"Data"},[]]}]],{"tag":"LamInternal","fields":[{"tag":"AnId","fields":[144]}]}]}},{"key":144,"value":{"tag":"AValNode","fields":[{"tag":"Datatype","fields":[{"tyName":"Data"},[]]},{"tag":"App","fields":[44,[{"tag":"AnId","fields":[92]},{"tag":"AnId","fields":[90]},{"tag":"AnId","fields":[143]}],[{"tag":"Nowhere"}],[0,[{"tag":"BuiltinFlat","fields":[{"tag":"BoolT"}]},{"tag":"Datatype","fields":[{"tyName":"Data"},[]]},{"tag":"Datatype","fields":[{"tyName":"Data"},[]]},{"tag":"Datatype","fields":[{"tyName":"Data"},[]]}]]]}]}},{"key":143,"value":{"tag":"AValNode","fields":[{"tag":"Datatype","fields":[{"tyName":"Data"},[]]},{"tag":"App","fields":[142,[{"tag":"AnId","fields":[88]}],[],[0,[{"tag":"Datatype","fields":[{"tyName":"Data"},[]]},{"tag":"Datatype","fields":[{"tyName":"Data"},[]]}]]]}]}},{"key":142,"value":{"tag":"ACompNode","fields":[[0,[{"tag":"Datatype","fields":[{"tyName":"Data"},[]]},{"tag":"Datatype","fields":[{"tyName":"Data"},[]]}]],{"tag":"ForceInternal","fields":[{"tag":"AnId","fields":[141]}]}]}},{"key":141,"value":{"tag":"AValNode","fields":[{"tag":"ThunkT","fields":[[0,[{"tag":"Datatype","fields":[{"tyName":"Data"},[]]},{"tag":"Datatype","fields":[{"tyName":"Data"},[]]}]]]},{"tag":"App","fields":[44,[{"tag":"AnId","fields":[95]},{"tag":"AnId","fields":[54]},{"tag":"AnId","fields":[140]}],[{"tag":"Nowhere"}],[0,[{"tag":"BuiltinFlat","fields":[{"tag":"BoolT"}]},{"tag":"ThunkT","fields":[[0,[{"tag":"Datatype","fields":[{"tyName":"Data"},[]]},{"tag":"Datatype","fields":[{"tyName":"Data"},[]]}]]]},{"tag":"ThunkT","fields":[[0,[{"tag":"Datatype","fields":[{"tyName":"Data"},[]]},{"tag":"Datatype","fields":[{"tyName":"Data"},[]]}]]]},{"tag":"ThunkT","fields":[[0,[{"tag":"Datatype","fields":[{"tyName":"Data"},[]]},{"tag":"Datatype","fields":[{"tyName":"Data"},[]]}]]]}]]]}]}},{"key":140,"value":{"tag":"AValNode","fields":[{"tag":"ThunkT","fields":[[0,[{"tag":"Datatype","fields":[{"tyName":"Data"},[]]},{"tag":"Datatype","fields":[{"tyName":"Data"},[]]}]]]},{"tag":"Thunk","fields":[139]}]}},{"key":139,"value":{"tag":"ACompNode","fields":[[0,[{"tag":"Datatype","fields":[{"tyName":"Data"},[]]},{"tag":"Datatype","fields":[{"tyName":"Data"},[]]}]],{"tag":"LamInternal","fields":[{"tag":"AnId","fields":[138]}]}]}},{"key":138,"value":{"tag":"AValNode","fields":[{"tag":"Datatype","fields":[{"tyName":"Data"},[]]},{"tag":"App","fields":[44,[{"tag":"AnId","fields":[92]},{"tag":"AnId","fields":[90]},{"tag":"AnId","fields":[137]}],[{"tag":"Nowhere"}],[0,[{"tag":"BuiltinFlat","fields":[{"tag":"BoolT"}]},{"tag":"Datatype","fields":[{"tyName":"Data"},[]]},{"tag":"Datatype","fields":[{"tyName":"Data"},[]]},{"tag":"Datatype","fields":[{"tyName":"Data"},[]]}]]]}]}},{"key":137,"value":{"tag":"AValNode","fields":[{"tag":"Datatype","fields":[{"tyName":"Data"},[]]},{"tag":"App","fields":[136,[{"tag":"AnId","fields":[88]}],[],[0,[{"tag":"Datatype","fields":[{"tyName":"Data"},[]]},{"tag":"Datatype","fields":[{"tyName":"Data"},[]]}]]]}]}},{"key":136,"value":{"tag":"ACompNode","fields":[[0,[{"tag":"Datatype","fields":[{"tyName":"Data"},[]]},{"tag":"Datatype","fields":[{"tyName":"Data"},[]]}]],{"tag":"ForceInternal","fields":[{"tag":"AnId","fields":[135]}]}]}},{"key":135,"value":{"tag":"AValNode","fields":[{"tag":"ThunkT","fields":[[0,[{"tag":"Datatype","fields":[{"tyName":"Data"},[]]},{"tag":"Datatype","fields":[{"tyName":"Data"},[]]}]]]},{"tag":"App","fields":[44,[{"tag":"AnId","fields":[95]},{"tag":"AnId","fields":[54]},{"tag":"AnId","fields":[134]}],[{"tag":"Nowhere"}],[0,[{"tag":"BuiltinFlat","fields":[{"tag":"BoolT"}]},{"tag":"ThunkT","fields":[[0,[{"tag":"Datatype","fields":[{"tyName":"Data"},[]]},{"tag":"Datatype","fields":[{"tyName":"Data"},[]]}]]]},{"tag":"ThunkT","fields":[[0,[{"tag":"Datatype","fields":[{"tyName":"Data"},[]]},{"tag":"Datatype","fields":[{"tyName":"Data"},[]]}]]]},{"tag":"ThunkT","fields":[[0,[{"tag":"Datatype","fields":[{"tyName":"Data"},[]]},{"tag":"Datatype","fields":[{"tyName":"Data"},[]]}]]]}]]]}]}},{"key":134,"value":{"tag":"AValNode","fields":[{"tag":"ThunkT","fields":[[0,[{"tag":"Datatype","fields":[{"tyName":"Data"},[]]},{"tag":"Datatype","fields":[{"tyName":"Data"},[]]}]]]},{"tag":"Thunk","fields":[133]}]}},{"key":133,"value":{"tag":"ACompNode","fields":[[0,[{"tag":"Datatype","fields":[{"tyName":"Data"},[]]},{"tag":"Datatype","fields":[{"tyName":"Data"},[]]}]],{"tag":"LamInternal","fields":[{"tag":"AnId","fields":[132]}]}]}},{"key":132,"value":{"tag":"AValNode","fields":[{"tag":"Datatype","fields":[{"tyName":"Data"},[]]},{"tag":"App","fields":[44,[{"tag":"AnId","fields":[92]},{"tag":"AnId","fields":[90]},{"tag":"AnId","fields":[131]}],[{"tag":"Nowhere"}],[0,[{"tag":"BuiltinFlat","fields":[{"tag":"BoolT"}]},{"tag":"Datatype","fields":[{"tyName":"Data"},[]]},{"tag":"Datatype","fields":[{"tyName":"Data"},[]]},{"tag":"Datatype","fields":[{"tyName":"Data"},[]]}]]]}]}},{"key":131,"value":{"tag":"AValNode","fields":[{"tag":"Datatype","fields":[{"tyName":"Data"},[]]},{"tag":"App","fields":[130,[{"tag":"AnId","fields":[88]}],[],[0,[{"tag":"Datatype","fields":[{"tyName":"Data"},[]]},{"tag":"Datatype","fields":[{"tyName":"Data"},[]]}]]]}]}},{"key":130,"value":{"tag":"ACompNode","fields":[[0,[{"tag":"Datatype","fields":[{"tyName":"Data"},[]]},{"tag":"Datatype","fields":[{"tyName":"Data"},[]]}]],{"tag":"ForceInternal","fields":[{"tag":"AnId","fields":[129]}]}]}},{"key":129,"value":{"tag":"AValNode","fields":[{"tag":"ThunkT","fields":[[0,[{"tag":"Datatype","fields":[{"tyName":"Data"},[]]},{"tag":"Datatype","fields":[{"tyName":"Data"},[]]}]]]},{"tag":"App","fields":[44,[{"tag":"AnId","fields":[95]},{"tag":"AnId","fields":[54]},{"tag":"AnId","fields":[128]}],[{"tag":"Nowhere"}],[0,[{"tag":"BuiltinFlat","fields":[{"tag":"BoolT"}]},{"tag":"ThunkT","fields":[[0,[{"tag":"Datatype","fields":[{"tyName":"Data"},[]]},{"tag":"Datatype","fields":[{"tyName":"Data"},[]]}]]]},{"tag":"ThunkT","fields":[[0,[{"tag":"Datatype","fields":[{"tyName":"Data"},[]]},{"tag":"Datatype","fields":[{"tyName":"Data"},[]]}]]]},{"tag":"ThunkT","fields":[[0,[{"tag":"Datatype","fields":[{"tyName":"Data"},[]]},{"tag":"Datatype","fields":[{"tyName":"Data"},[]]}]]]}]]]}]}},{"key":128,"value":{"tag":"AValNode","fields":[{"tag":"ThunkT","fields":[[0,[{"tag":"Datatype","fields":[{"tyName":"Data"},[]]},{"tag":"Datatype","fields":[{"tyName":"Data"},[]]}]]]},{"tag":"Thunk","fields":[127]}]}},{"key":127,"value":{"tag":"ACompNode","fields":[[0,[{"tag":"Datatype","fields":[{"tyName":"Data"},[]]},{"tag":"Datatype","fields":[{"tyName":"Data"},[]]}]],{"tag":"LamInternal","fields":[{"tag":"AnId","fields":[126]}]}]}},{"key":126,"value":{"tag":"AValNode","fields":[{"tag":"Datatype","fields":[{"tyName":"Data"},[]]},{"tag":"App","fields":[44,[{"tag":"AnId","fields":[92]},{"tag":"AnId","fields":[90]},{"tag":"AnId","fields":[125]}],[{"tag":"Nowhere"}],[0,[{"tag":"BuiltinFlat","fields":[{"tag":"BoolT"}]},{"tag":"Datatype","fields":[{"tyName":"Data"},[]]},{"tag":"Datatype","fields":[{"tyName":"Data"},[]]},{"tag":"Datatype","fields":[{"tyName":"Data"},[]]}]]]}]}},{"key":125,"value":{"tag":"AValNode","fields":[{"tag":"Datatype","fields":[{"tyName":"Data"},[]]},{"tag":"App","fields":[124,[{"tag":"AnId","fields":[88]}],[],[0,[{"tag":"Datatype","fields":[{"tyName":"Data"},[]]},{"tag":"Datatype","fields":[{"tyName":"Data"},[]]}]]]}]}},{"key":124,"value":{"tag":"ACompNode","fields":[[0,[{"tag":"Datatype","fields":[{"tyName":"Data"},[]]},{"tag":"Datatype","fields":[{"tyName":"Data"},[]]}]],{"tag":"ForceInternal","fields":[{"tag":"AnId","fields":[123]}]}]}},{"key":123,"value":{"tag":"AValNode","fields":[{"tag":"ThunkT","fields":[[0,[{"tag":"Datatype","fields":[{"tyName":"Data"},[]]},{"tag":"Datatype","fields":[{"tyName":"Data"},[]]}]]]},{"tag":"App","fields":[44,[{"tag":"AnId","fields":[95]},{"tag":"AnId","fields":[54]},{"tag":"AnId","fields":[122]}],[{"tag":"Nowhere"}],[0,[{"tag":"BuiltinFlat","fields":[{"tag":"BoolT"}]},{"tag":"ThunkT","fields":[[0,[{"tag":"Datatype","fields":[{"tyName":"Data"},[]]},{"tag":"Datatype","fields":[{"tyName":"Data"},[]]}]]]},{"tag":"ThunkT","fields":[[0,[{"tag":"Datatype","fields":[{"tyName":"Data"},[]]},{"tag":"Datatype","fields":[{"tyName":"Data"},[]]}]]]},{"tag":"ThunkT","fields":[[0,[{"tag":"Datatype","fields":[{"tyName":"Data"},[]]},{"tag":"Datatype","fields":[{"tyName":"Data"},[]]}]]]}]]]}]}},{"key":122,"value":{"tag":"AValNode","fields":[{"tag":"ThunkT","fields":[[0,[{"tag":"Datatype","fields":[{"tyName":"Data"},[]]},{"tag":"Datatype","fields":[{"tyName":"Data"},[]]}]]]},{"tag":"Thunk","fields":[121]}]}},{"key":121,"value":{"tag":"ACompNode","fields":[[0,[{"tag":"Datatype","fields":[{"tyName":"Data"},[]]},{"tag":"Datatype","fields":[{"tyName":"Data"},[]]}]],{"tag":"LamInternal","fields":[{"tag":"AnId","fields":[120]}]}]}},{"key":120,"value":{"tag":"AValNode","fields":[{"tag":"Datatype","fields":[{"tyName":"Data"},[]]},{"tag":"App","fields":[44,[{"tag":"AnId","fields":[92]},{"tag":"AnId","fields":[90]},{"tag":"AnId","fields":[119]}],[{"tag":"Nowhere"}],[0,[{"tag":"BuiltinFlat","fields":[{"tag":"BoolT"}]},{"tag":"Datatype","fields":[{"tyName":"Data"},[]]},{"tag":"Datatype","fields":[{"tyName":"Data"},[]]},{"tag":"Datatype","fields":[{"tyName":"Data"},[]]}]]]}]}},{"key":119,"value":{"tag":"AValNode","fields":[{"tag":"Datatype","fields":[{"tyName":"Data"},[]]},{"tag":"App","fields":[118,[{"tag":"AnId","fields":[88]}],[],[0,[{"tag":"Datatype","fields":[{"tyName":"Data"},[]]},{"tag":"Datatype","fields":[{"tyName":"Data"},[]]}]]]}]}},{"key":118,"value":{"tag":"ACompNode","fields":[[0,[{"tag":"Datatype","fields":[{"tyName":"Data"},[]]},{"tag":"Datatype","fields":[{"tyName":"Data"},[]]}]],{"tag":"ForceInternal","fields":[{"tag":"AnId","fields":[117]}]}]}},{"key":117,"value":{"tag":"AValNode","fields":[{"tag":"ThunkT","fields":[[0,[{"tag":"Datatype","fields":[{"tyName":"Data"},[]]},{"tag":"Datatype","fields":[{"tyName":"Data"},[]]}]]]},{"tag":"App","fields":[44,[{"tag":"AnId","fields":[95]},{"tag":"AnId","fields":[54]},{"tag":"AnId","fields":[116]}],[{"tag":"Nowhere"}],[0,[{"tag":"BuiltinFlat","fields":[{"tag":"BoolT"}]},{"tag":"ThunkT","fields":[[0,[{"tag":"Datatype","fields":[{"tyName":"Data"},[]]},{"tag":"Datatype","fields":[{"tyName":"Data"},[]]}]]]},{"tag":"ThunkT","fields":[[0,[{"tag":"Datatype","fields":[{"tyName":"Data"},[]]},{"tag":"Datatype","fields":[{"tyName":"Data"},[]]}]]]},{"tag":"ThunkT","fields":[[0,[{"tag":"Datatype","fields":[{"tyName":"Data"},[]]},{"tag":"Datatype","fields":[{"tyName":"Data"},[]]}]]]}]]]}]}},{"key":116,"value":{"tag":"AValNode","fields":[{"tag":"ThunkT","fields":[[0,[{"tag":"Datatype","fields":[{"tyName":"Data"},[]]},{"tag":"Datatype","fields":[{"tyName":"Data"},[]]}]]]},{"tag":"Thunk","fields":[115]}]}},{"key":115,"value":{"tag":"ACompNode","fields":[[0,[{"tag":"Datatype","fields":[{"tyName":"Data"},[]]},{"tag":"Datatype","fields":[{"tyName":"Data"},[]]}]],{"tag":"LamInternal","fields":[{"tag":"AnId","fields":[114]}]}]}},{"key":114,"value":{"tag":"AValNode","fields":[{"tag":"Datatype","fields":[{"tyName":"Data"},[]]},{"tag":"App","fields":[44,[{"tag":"AnId","fields":[92]},{"tag":"AnId","fields":[90]},{"tag":"AnId","fields":[113]}],[{"tag":"Nowhere"}],[0,[{"tag":"BuiltinFlat","fields":[{"tag":"BoolT"}]},{"tag":"Datatype","fields":[{"tyName":"Data"},[]]},{"tag":"Datatype","fields":[{"tyName":"Data"},[]]},{"tag":"Datatype","fields":[{"tyName":"Data"},[]]}]]]}]}},{"key":113,"value":{"tag":"AValNode","fields":[{"tag":"Datatype","fields":[{"tyName":"Data"},[]]},{"tag":"App","fields":[112,[{"tag":"AnId","fields":[88]}],[],[0,[{"tag":"Datatype","fields":[{"tyName":"Data"},[]]},{"tag":"Datatype","fields":[{"tyName":"Data"},[]]}]]]}]}},{"key":112,"value":{"tag":"ACompNode","fields":[[0,[{"tag":"Datatype","fields":[{"tyName":"Data"},[]]},{"tag":"Datatype","fields":[{"tyName":"Data"},[]]}]],{"tag":"ForceInternal","fields":[{"tag":"AnId","fields":[111]}]}]}},{"key":111,"value":{"tag":"AValNode","fields":[{"tag":"ThunkT","fields":[[0,[{"tag":"Datatype","fields":[{"tyName":"Data"},[]]},{"tag":"Datatype","fields":[{"tyName":"Data"},[]]}]]]},{"tag":"App","fields":[44,[{"tag":"AnId","fields":[95]},{"tag":"AnId","fields":[54]},{"tag":"AnId","fields":[110]}],[{"tag":"Nowhere"}],[0,[{"tag":"BuiltinFlat","fields":[{"tag":"BoolT"}]},{"tag":"ThunkT","fields":[[0,[{"tag":"Datatype","fields":[{"tyName":"Data"},[]]},{"tag":"Datatype","fields":[{"tyName":"Data"},[]]}]]]},{"tag":"ThunkT","fields":[[0,[{"tag":"Datatype","fields":[{"tyName":"Data"},[]]},{"tag":"Datatype","fields":[{"tyName":"Data"},[]]}]]]},{"tag":"ThunkT","fields":[[0,[{"tag":"Datatype","fields":[{"tyName":"Data"},[]]},{"tag":"Datatype","fields":[{"tyName":"Data"},[]]}]]]}]]]}]}},{"key":110,"value":{"tag":"AValNode","fields":[{"tag":"ThunkT","fields":[[0,[{"tag":"Datatype","fields":[{"tyName":"Data"},[]]},{"tag":"Datatype","fields":[{"tyName":"Data"},[]]}]]]},{"tag":"Thunk","fields":[109]}]}},{"key":109,"value":{"tag":"ACompNode","fields":[[0,[{"tag":"Datatype","fields":[{"tyName":"Data"},[]]},{"tag":"Datatype","fields":[{"tyName":"Data"},[]]}]],{"tag":"LamInternal","fields":[{"tag":"AnId","fields":[108]}]}]}},{"key":108,"value":{"tag":"AValNode","fields":[{"tag":"Datatype","fields":[{"tyName":"Data"},[]]},{"tag":"App","fields":[44,[{"tag":"AnId","fields":[92]},{"tag":"AnId","fields":[90]},{"tag":"AnId","fields":[107]}],[{"tag":"Nowhere"}],[0,[{"tag":"BuiltinFlat","fields":[{"tag":"BoolT"}]},{"tag":"Datatype","fields":[{"tyName":"Data"},[]]},{"tag":"Datatype","fields":[{"tyName":"Data"},[]]},{"tag":"Datatype","fields":[{"tyName":"Data"},[]]}]]]}]}},{"key":107,"value":{"tag":"AValNode","fields":[{"tag":"Datatype","fields":[{"tyName":"Data"},[]]},{"tag":"App","fields":[106,[{"tag":"AnId","fields":[88]}],[],[0,[{"tag":"Datatype","fields":[{"tyName":"Data"},[]]},{"tag":"Datatype","fields":[{"tyName":"Data"},[]]}]]]}]}},{"key":106,"value":{"tag":"ACompNode","fields":[[0,[{"tag":"Datatype","fields":[{"tyName":"Data"},[]]},{"tag":"Datatype","fields":[{"tyName":"Data"},[]]}]],{"tag":"ForceInternal","fields":[{"tag":"AnId","fields":[105]}]}]}},{"key":105,"value":{"tag":"AValNode","fields":[{"tag":"ThunkT","fields":[[0,[{"tag":"Datatype","fields":[{"tyName":"Data"},[]]},{"tag":"Datatype","fields":[{"tyName":"Data"},[]]}]]]},{"tag":"App","fields":[44,[{"tag":"AnId","fields":[95]},{"tag":"AnId","fields":[54]},{"tag":"AnId","fields":[104]}],[{"tag":"Nowhere"}],[0,[{"tag":"BuiltinFlat","fields":[{"tag":"BoolT"}]},{"tag":"ThunkT","fields":[[0,[{"tag":"Datatype","fields":[{"tyName":"Data"},[]]},{"tag":"Datatype","fields":[{"tyName":"Data"},[]]}]]]},{"tag":"ThunkT","fields":[[0,[{"tag":"Datatype","fields":[{"tyName":"Data"},[]]},{"tag":"Datatype","fields":[{"tyName":"Data"},[]]}]]]},{"tag":"ThunkT","fields":[[0,[{"tag":"Datatype","fields":[{"tyName":"Data"},[]]},{"tag":"Datatype","fields":[{"tyName":"Data"},[]]}]]]}]]]}]}},{"key":104,"value":{"tag":"AValNode","fields":[{"tag":"ThunkT","fields":[[0,[{"tag":"Datatype","fields":[{"tyName":"Data"},[]]},{"tag":"Datatype","fields":[{"tyName":"Data"},[]]}]]]},{"tag":"Thunk","fields":[103]}]}},{"key":103,"value":{"tag":"ACompNode","fields":[[0,[{"tag":"Datatype","fields":[{"tyName":"Data"},[]]},{"tag":"Datatype","fields":[{"tyName":"Data"},[]]}]],{"tag":"LamInternal","fields":[{"tag":"AnId","fields":[102]}]}]}},{"key":102,"value":{"tag":"AValNode","fields":[{"tag":"Datatype","fields":[{"tyName":"Data"},[]]},{"tag":"App","fields":[44,[{"tag":"AnId","fields":[92]},{"tag":"AnId","fields":[90]},{"tag":"AnId","fields":[101]}],[{"tag":"Nowhere"}],[0,[{"tag":"BuiltinFlat","fields":[{"tag":"BoolT"}]},{"tag":"Datatype","fields":[{"tyName":"Data"},[]]},{"tag":"Datatype","fields":[{"tyName":"Data"},[]]},{"tag":"Datatype","fields":[{"tyName":"Data"},[]]}]]]}]}},{"key":101,"value":{"tag":"AValNode","fields":[{"tag":"Datatype","fields":[{"tyName":"Data"},[]]},{"tag":"App","fields":[100,[{"tag":"AnId","fields":[88]}],[],[0,[{"tag":"Datatype","fields":[{"tyName":"Data"},[]]},{"tag":"Datatype","fields":[{"tyName":"Data"},[]]}]]]}]}},{"key":100,"value":{"tag":"ACompNode","fields":[[0,[{"tag":"Datatype","fields":[{"tyName":"Data"},[]]},{"tag":"Datatype","fields":[{"tyName":"Data"},[]]}]],{"tag":"ForceInternal","fields":[{"tag":"AnId","fields":[99]}]}]}},{"key":99,"value":{"tag":"AValNode","fields":[{"tag":"ThunkT","fields":[[0,[{"tag":"Datatype","fields":[{"tyName":"Data"},[]]},{"tag":"Datatype","fields":[{"tyName":"Data"},[]]}]]]},{"tag":"App","fields":[44,[{"tag":"AnId","fields":[95]},{"tag":"AnId","fields":[54]},{"tag":"AnId","fields":[98]}],[{"tag":"Nowhere"}],[0,[{"tag":"BuiltinFlat","fields":[{"tag":"BoolT"}]},{"tag":"ThunkT","fields":[[0,[{"tag":"Datatype","fields":[{"tyName":"Data"},[]]},{"tag":"Datatype","fields":[{"tyName":"Data"},[]]}]]]},{"tag":"ThunkT","fields":[[0,[{"tag":"Datatype","fields":[{"tyName":"Data"},[]]},{"tag":"Datatype","fields":[{"tyName":"Data"},[]]}]]]},{"tag":"ThunkT","fields":[[0,[{"tag":"Datatype","fields":[{"tyName":"Data"},[]]},{"tag":"Datatype","fields":[{"tyName":"Data"},[]]}]]]}]]]}]}},{"key":98,"value":{"tag":"AValNode","fields":[{"tag":"ThunkT","fields":[[0,[{"tag":"Datatype","fields":[{"tyName":"Data"},[]]},{"tag":"Datatype","fields":[{"tyName":"Data"},[]]}]]]},{"tag":"Thunk","fields":[97]}]}},{"key":97,"value":{"tag":"ACompNode","fields":[[0,[{"tag":"Datatype","fields":[{"tyName":"Data"},[]]},{"tag":"Datatype","fields":[{"tyName":"Data"},[]]}]],{"tag":"LamInternal","fields":[{"tag":"AnId","fields":[96]}]}]}},{"key":96,"value":{"tag":"AValNode","fields":[{"tag":"Datatype","fields":[{"tyName":"Data"},[]]},{"tag":"App","fields":[44,[{"tag":"AnId","fields":[92]},{"tag":"AnId","fields":[90]},{"tag":"AnId","fields":[52]}],[{"tag":"Nowhere"}],[0,[{"tag":"BuiltinFlat","fields":[{"tag":"BoolT"}]},{"tag":"Datatype","fields":[{"tyName":"Data"},[]]},{"tag":"Datatype","fields":[{"tyName":"Data"},[]]},{"tag":"Datatype","fields":[{"tyName":"Data"},[]]}]]]}]}},{"key":95,"value":{"tag":"AValNode","fields":[{"tag":"BuiltinFlat","fields":[{"tag":"BoolT"}]},{"tag":"App","fields":[43,[{"tag":"AnId","fields":[94]}],[{"tag":"Nowhere"}],[0,[{"tag":"Datatype","fields":[{"tyName":"List"},[{"tag":"Datatype","fields":[{"tyName":"Pair"},[{"tag":"Datatype","fields":[{"tyName":"Data"},[]]},{"tag":"Datatype","fields":[{"tyName":"Data"},[]]}]]}]]},{"tag":"BuiltinFlat","fields":[{"tag":"BoolT"}]}]]]}]}},{"key":94,"value":{"tag":"AValNode","fields":[{"tag":"Datatype","fields":[{"tyName":"List"},[{"tag":"Datatype","fields":[{"tyName":"Pair"},[{"tag":"Datatype","fields":[{"tyName":"Data"},[]]},{"tag":"Datatype","fields":[{"tyName":"Data"},[]]}]]}]]},{"tag":"App","fields":[4,[{"tag":"AnId","fields":[93]}],[{"tag":"Nowhere"}],[0,[{"tag":"Datatype","fields":[{"tyName":"List"},[{"tag":"Datatype","fields":[{"tyName":"Pair"},[{"tag":"Datatype","fields":[{"tyName":"Data"},[]]},{"tag":"Datatype","fields":[{"tyName":"Data"},[]]}]]}]]},{"tag":"Datatype","fields":[{"tyName":"List"},[{"tag":"Datatype","fields":[{"tyName":"Pair"},[{"tag":"Datatype","fields":[{"tyName":"Data"},[]]},{"tag":"Datatype","fields":[{"tyName":"Data"},[]]}]]}]]}]]]}]}},{"key":93,"value":{"tag":"AValNode","fields":[{"tag":"Datatype","fields":[{"tyName":"List"},[{"tag":"Datatype","fields":[{"tyName":"Pair"},[{"tag":"Datatype","fields":[{"tyName":"Data"},[]]},{"tag":"Datatype","fields":[{"tyName":"Data"},[]]}]]}]]},{"tag":"App","fields":[69,[{"tag":"AnId","fields":[88]}],[],[0,[{"tag":"Datatype","fields":[{"tyName":"Data"},[]]},{"tag":"Datatype","fields":[{"tyName":"List"},[{"tag":"Datatype","fields":[{"tyName":"Pair"},[{"tag":"Datatype","fields":[{"tyName":"Data"},[]]},{"tag":"Datatype","fields":[{"tyName":"Data"},[]]}]]}]]}]]]}]}},{"key":92,"value":{"tag":"AValNode","fields":[{"tag":"BuiltinFlat","fields":[{"tag":"BoolT"}]},{"tag":"App","fields":[91,[{"tag":"AnId","fields":[89]},{"tag":"AnId","fields":[82]}],[],[0,[{"tag":"Datatype","fields":[{"tyName":"Data"},[]]},{"tag":"Datatype","fields":[{"tyName":"Data"},[]]},{"tag":"BuiltinFlat","fields":[{"tag":"BoolT"}]}]]]}]}},{"key":91,"value":{"tag":"ACompNode","fields":[[0,[{"tag":"Datatype","fields":[{"tyName":"Data"},[]]},{"tag":"Datatype","fields":[{"tyName":"Data"},[]]},{"tag":"BuiltinFlat","fields":[{"tag":"BoolT"}]}]],{"tag":"Builtin2Internal","fields":[{"tag":"EqualsData"}]}]}},{"key":90,"value":{"tag":"AValNode","fields":[{"tag":"Datatype","fields":[{"tyName":"Data"},[]]},{"tag":"App","fields":[2,[{"tag":"AnId","fields":[84]}],[{"tag":"Nowhere"},{"tag":"Nowhere"}],[0,[{"tag":"Datatype","fields":[{"tyName":"Pair"},[{"tag":"Datatype","fields":[{"tyName":"Data"},[]]},{"tag":"Datatype","fields":[{"tyName":"Data"},[]]}]]},{"tag":"Datatype","fields":[{"tyName":"Data"},[]]}]]]}]}},{"key":89,"value":{"tag":"AValNode","fields":[{"tag":"Datatype","fields":[{"tyName":"Data"},[]]},{"tag":"App","fields":[76,[{"tag":"AnId","fields":[84]}],[{"tag":"Nowhere"},{"tag":"Nowhere"}],[0,[{"tag":"Datatype","fields":[{"tyName":"Pair"},[{"tag":"Datatype","fields":[{"tyName":"Data"},[]]},{"tag":"Datatype","fields":[{"tyName":"Data"},[]]}]]},{"tag":"Datatype","fields":[{"tyName":"Data"},[]]}]]]}]}},{"key":88,"value":{"tag":"AValNode","fields":[{"tag":"Datatype","fields":[{"tyName":"Data"},[]]},{"tag":"App","fields":[74,[{"tag":"AnId","fields":[87]}],[],[0,[{"tag":"Datatype","fields":[{"tyName":"List"},[{"tag":"Datatype","fields":[{"tyName":"Pair"},[{"tag":"Datatype","fields":[{"tyName":"Data"},[]]},{"tag":"Datatype","fields":[{"tyName":"Data"},[]]}]]}]]},{"tag":"Datatype","fields":[{"tyName":"Data"},[]]}]]]}]}},{"key":87,"value":{"tag":"AValNode","fields":[{"tag":"Datatype","fields":[{"tyName":"List"},[{"tag":"Datatype","fields":[{"tyName":"Pair"},[{"tag":"Datatype","fields":[{"tyName":"Data"},[]]},{"tag":"Datatype","fields":[{"tyName":"Data"},[]]}]]}]]},{"tag":"App","fields":[25,[{"tag":"AnId","fields":[86]},{"tag":"AnId","fields":[85]}],[{"tag":"Nowhere"}],[0,[{"tag":"Datatype","fields":[{"tyName":"Pair"},[{"tag":"Datatype","fields":[{"tyName":"Data"},[]]},{"tag":"Datatype","fields":[{"tyName":"Data"},[]]}]]},{"tag":"Datatype","fields":[{"tyName":"List"},[{"tag":"Datatype","fields":[{"tyName":"Pair"},[{"tag":"Datatype","fields":[{"tyName":"Data"},[]]},{"tag":"Datatype","fields":[{"tyName":"Data"},[]]}]]}]]},{"tag":"Datatype","fields":[{"tyName":"List"},[{"tag":"Datatype","fields":[{"tyName":"Pair"},[{"tag":"Datatype","fields":[{"tyName":"Data"},[]]},{"tag":"Datatype","fields":[{"tyName":"Data"},[]]}]]}]]}]]]}]}},{"key":86,"value":{"tag":"AValNode","fields":[{"tag":"Datatype","fields":[{"tyName":"Pair"},[{"tag":"Datatype","fields":[{"tyName":"Data"},[]]},{"tag":"Datatype","fields":[{"tyName":"Data"},[]]}]]},{"tag":"App","fields":[71,[{"tag":"AnId","fields":[82]},{"tag":"AnId","fields":[82]}],[],[0,[{"tag":"Datatype","fields":[{"tyName":"Data"},[]]},{"tag":"Datatype","fields":[{"tyName":"Data"},[]]},{"tag":"Datatype","fields":[{"tyName":"Pair"},[{"tag":"Datatype","fields":[{"tyName":"Data"},[]]},{"tag":"Datatype","fields":[{"tyName":"Data"},[]]}]]}]]]}]}},{"key":85,"value":{"tag":"AValNode","fields":[{"tag":"Datatype","fields":[{"tyName":"List"},[{"tag":"Datatype","fields":[{"tyName":"Pair"},[{"tag":"Datatype","fields":[{"tyName":"Data"},[]]},{"tag":"Datatype","fields":[{"tyName":"Data"},[]]}]]}]]},{"tag":"App","fields":[4,[{"tag":"AnId","fields":[83]}],[{"tag":"Nowhere"}],[0,[{"tag":"Datatype","fields":[{"tyName":"List"},[{"tag":"Datatype","fields":[{"tyName":"Pair"},[{"tag":"Datatype","fields":[{"tyName":"Data"},[]]},{"tag":"Datatype","fields":[{"tyName":"Data"},[]]}]]}]]},{"tag":"Datatype","fields":[{"tyName":"List"},[{"tag":"Datatype","fields":[{"tyName":"Pair"},[{"tag":"Datatype","fields":[{"tyName":"Data"},[]]},{"tag":"Datatype","fields":[{"tyName":"Data"},[]]}]]}]]}]]]}]}},{"key":84,"value":{"tag":"AValNode","fields":[{"tag":"Datatype","fields":[{"tyName":"Pair"},[{"tag":"Datatype","fields":[{"tyName":"Data"},[]]},{"tag":"Datatype","fields":[{"tyName":"Data"},[]]}]]},{"tag":"App","fields":[7,[{"tag":"AnId","fields":[83]}],[{"tag":"Nowhere"}],[0,[{"tag":"Datatype","fields":[{"tyName":"List"},[{"tag":"Datatype","fields":[{"tyName":"Pair"},[{"tag":"Datatype","fields":[{"tyName":"Data"},[]]},{"tag":"Datatype","fields":[{"tyName":"Data"},[]]}]]}]]},{"tag":"Datatype","fields":[{"tyName":"Pair"},[{"tag":"Datatype","fields":[{"tyName":"Data"},[]]},{"tag":"Datatype","fields":[{"tyName":"Data"},[]]}]]}]]]}]}},{"key":83,"value":{"tag":"AValNode","fields":[{"tag":"Datatype","fields":[{"tyName":"List"},[{"tag":"Datatype","fields":[{"tyName":"Pair"},[{"tag":"Datatype","fields":[{"tyName":"Data"},[]]},{"tag":"Datatype","fields":[{"tyName":"Data"},[]]}]]}]]},{"tag":"App","fields":[4,[{"tag":"AnId","fields":[80]}],[{"tag":"Nowhere"}],[0,[{"tag":"Datatype","fields":[{"tyName":"List"},[{"tag":"Datatype","fields":[{"tyName":"Pair"},[{"tag":"Datatype","fields":[{"tyName":"Data"},[]]},{"tag":"Datatype","fields":[{"tyName":"Data"},[]]}]]}]]},{"tag":"Datatype","fields":[{"tyName":"List"},[{"tag":"Datatype","fields":[{"tyName":"Pair"},[{"tag":"Datatype","fields":[{"tyName":"Data"},[]]},{"tag":"Datatype","fields":[{"tyName":"Data"},[]]}]]}]]}]]]}]}},{"key":82,"value":{"tag":"AValNode","fields":[{"tag":"Datatype","fields":[{"tyName":"Data"},[]]},{"tag":"App","fields":[76,[{"tag":"AnId","fields":[81]}],[{"tag":"Nowhere"},{"tag":"Nowhere"}],[0,[{"tag":"Datatype","fields":[{"tyName":"Pair"},[{"tag":"Datatype","fields":[{"tyName":"Data"},[]]},{"tag":"Datatype","fields":[{"tyName":"Data"},[]]}]]},{"tag":"Datatype","fields":[{"tyName":"Data"},[]]}]]]}]}},{"key":81,"value":{"tag":"AValNode","fields":[{"tag":"Datatype","fields":[{"tyName":"Pair"},[{"tag":"Datatype","fields":[{"tyName":"Data"},[]]},{"tag":"Datatype","fields":[{"tyName":"Data"},[]]}]]},{"tag":"App","fields":[7,[{"tag":"AnId","fields":[80]}],[{"tag":"Nowhere"}],[0,[{"tag":"Datatype","fields":[{"tyName":"List"},[{"tag":"Datatype","fields":[{"tyName":"Pair"},[{"tag":"Datatype","fields":[{"tyName":"Data"},[]]},{"tag":"Datatype","fields":[{"tyName":"Data"},[]]}]]}]]},{"tag":"Datatype","fields":[{"tyName":"Pair"},[{"tag":"Datatype","fields":[{"tyName":"Data"},[]]},{"tag":"Datatype","fields":[{"tyName":"Data"},[]]}]]}]]]}]}},{"key":80,"value":{"tag":"AValNode","fields":[{"tag":"Datatype","fields":[{"tyName":"List"},[{"tag":"Datatype","fields":[{"tyName":"Pair"},[{"tag":"Datatype","fields":[{"tyName":"Data"},[]]},{"tag":"Datatype","fields":[{"tyName":"Data"},[]]}]]}]]},{"tag":"App","fields":[69,[{"tag":"AnArg","fields":[{"argDeBruijn":0,"argIndex":0,"argType":{"tag":"Datatype","fields":[{"tyName":"Data"},[]]}}]}],[],[0,[{"tag":"Datatype","fields":[{"tyName":"Data"},[]]},{"tag":"Datatype","fields":[{"tyName":"List"},[{"tag":"Datatype","fields":[{"tyName":"Pair"},[{"tag":"Datatype","fields":[{"tyName":"Data"},[]]},{"tag":"Datatype","fields":[{"tyName":"Data"},[]]}]]}]]}]]]}]}},{"key":79,"value":{"tag":"AValNode","fields":[{"tag":"BuiltinFlat","fields":[{"tag":"BoolT"}]},{"tag":"App","fields":[43,[{"tag":"AnId","fields":[78]}],[{"tag":"Nowhere"}],[0,[{"tag":"Datatype","fields":[{"tyName":"List"},[{"tag":"Datatype","fields":[{"tyName":"Pair"},[{"tag":"Datatype","fields":[{"tyName":"Data"},[]]},{"tag":"Datatype","fields":[{"tyName":"Data"},[]]}]]}]]},{"tag":"BuiltinFlat","fields":[{"tag":"BoolT"}]}]]]}]}},{"key":78,"value":{"tag":"AValNode","fields":[{"tag":"Datatype","fields":[{"tyName":"List"},[{"tag":"Datatype","fields":[{"tyName":"Pair"},[{"tag":"Datatype","fields":[{"tyName":"Data"},[]]},{"tag":"Datatype","fields":[{"tyName":"Data"},[]]}]]}]]},{"tag":"App","fields":[4,[{"tag":"AnId","fields":[77]}],[{"tag":"Nowhere"}],[0,[{"tag":"Datatype","fields":[{"tyName":"List"},[{"tag":"Datatype","fields":[{"tyName":"Pair"},[{"tag":"Datatype","fields":[{"tyName":"Data"},[]]},{"tag":"Datatype","fields":[{"tyName":"Data"},[]]}]]}]]},{"tag":"Datatype","fields":[{"tyName":"List"},[{"tag":"Datatype","fields":[{"tyName":"Pair"},[{"tag":"Datatype","fields":[{"tyName":"Data"},[]]},{"tag":"Datatype","fields":[{"tyName":"Data"},[]]}]]}]]}]]]}]}},{"key":77,"value":{"tag":"AValNode","fields":[{"tag":"Datatype","fields":[{"tyName":"List"},[{"tag":"Datatype","fields":[{"tyName":"Pair"},[{"tag":"Datatype","fields":[{"tyName":"Data"},[]]},{"tag":"Datatype","fields":[{"tyName":"Data"},[]]}]]}]]},{"tag":"App","fields":[69,[{"tag":"AnId","fields":[75]}],[],[0,[{"tag":"Datatype","fields":[{"tyName":"Data"},[]]},{"tag":"Datatype","fields":[{"tyName":"List"},[{"tag":"Datatype","fields":[{"tyName":"Pair"},[{"tag":"Datatype","fields":[{"tyName":"Data"},[]]},{"tag":"Datatype","fields":[{"tyName":"Data"},[]]}]]}]]}]]]}]}},{"key":76,"value":{"tag":"ACompNode","fields":[[2,[{"tag":"Datatype","fields":[{"tyName":"Pair"},[{"tag":"Abstraction","fields":[[0,0]]},{"tag":"Abstraction","fields":[[0,1]]}]]},{"tag":"Abstraction","fields":[[0,0]]}]],{"tag":"Builtin1Internal","fields":[{"tag":"FstPair"}]}]}},{"key":75,"value":{"tag":"AValNode","fields":[{"tag":"Datatype","fields":[{"tyName":"Data"},[]]},{"tag":"App","fields":[74,[{"tag":"AnId","fields":[73]}],[],[0,[{"tag":"Datatype","fields":[{"tyName":"List"},[{"tag":"Datatype","fields":[{"tyName":"Pair"},[{"tag":"Datatype","fields":[{"tyName":"Data"},[]]},{"tag":"Datatype","fields":[{"tyName":"Data"},[]]}]]}]]},{"tag":"Datatype","fields":[{"tyName":"Data"},[]]}]]]}]}},{"key":74,"value":{"tag":"ACompNode","fields":[[0,[{"tag":"Datatype","fields":[{"tyName":"List"},[{"tag":"Datatype","fields":[{"tyName":"Pair"},[{"tag":"Datatype","fields":[{"tyName":"Data"},[]]},{"tag":"Datatype","fields":[{"tyName":"Data"},[]]}]]}]]},{"tag":"Datatype","fields":[{"tyName":"Data"},[]]}]],{"tag":"Builtin1Internal","fields":[{"tag":"MapData"}]}]}},{"key":73,"value":{"tag":"AValNode","fields":[{"tag":"Datatype","fields":[{"tyName":"List"},[{"tag":"Datatype","fields":[{"tyName":"Pair"},[{"tag":"Datatype","fields":[{"tyName":"Data"},[]]},{"tag":"Datatype","fields":[{"tyName":"Data"},[]]}]]}]]},{"tag":"App","fields":[25,[{"tag":"AnId","fields":[72]},{"tag":"AnId","fields":[70]}],[{"tag":"Nowhere"}],[0,[{"tag":"Datatype","fields":[{"tyName":"Pair"},[{"tag":"Datatype","fields":[{"tyName":"Data"},[]]},{"tag":"Datatype","fields":[{"tyName":"Data"},[]]}]]},{"tag":"Datatype","fields":[{"tyName":"List"},[{"tag":"Datatype","fields":[{"tyName":"Pair"},[{"tag":"Datatype","fields":[{"tyName":"Data"},[]]},{"tag":"Datatype","fields":[{"tyName":"Data"},[]]}]]}]]},{"tag":"Datatype","fields":[{"tyName":"List"},[{"tag":"Datatype","fields":[{"tyName":"Pair"},[{"tag":"Datatype","fields":[{"tyName":"Data"},[]]},{"tag":"Datatype","fields":[{"tyName":"Data"},[]]}]]}]]}]]]}]}},{"key":72,"value":{"tag":"AValNode","fields":[{"tag":"Datatype","fields":[{"tyName":"Pair"},[{"tag":"Datatype","fields":[{"tyName":"Data"},[]]},{"tag":"Datatype","fields":[{"tyName":"Data"},[]]}]]},{"tag":"App","fields":[71,[{"tag":"AnId","fields":[63]},{"tag":"AnId","fields":[63]}],[],[0,[{"tag":"Datatype","fields":[{"tyName":"Data"},[]]},{"tag":"Datatype","fields":[{"tyName":"Data"},[]]},{"tag":"Datatype","fields":[{"tyName":"Pair"},[{"tag":"Datatype","fields":[{"tyName":"Data"},[]]},{"tag":"Datatype","fields":[{"tyName":"Data"},[]]}]]}]]]}]}},{"key":71,"value":{"tag":"ACompNode","fields":[[0,[{"tag":"Datatype","fields":[{"tyName":"Data"},[]]},{"tag":"Datatype","fields":[{"tyName":"Data"},[]]},{"tag":"Datatype","fields":[{"tyName":"Pair"},[{"tag":"Datatype","fields":[{"tyName":"Data"},[]]},{"tag":"Datatype","fields":[{"tyName":"Data"},[]]}]]}]],{"tag":"Builtin2Internal","fields":[{"tag":"MkPairData"}]}]}},{"key":70,"value":{"tag":"AValNode","fields":[{"tag":"Datatype","fields":[{"tyName":"List"},[{"tag":"Datatype","fields":[{"tyName":"Pair"},[{"tag":"Datatype","fields":[{"tyName":"Data"},[]]},{"tag":"Datatype","fields":[{"tyName":"Data"},[]]}]]}]]},{"tag":"App","fields":[69,[{"tag":"AnId","fields":[68]}],[],[0,[{"tag":"Datatype","fields":[{"tyName":"Data"},[]]},{"tag":"Datatype","fields":[{"tyName":"List"},[{"tag":"Datatype","fields":[{"tyName":"Pair"},[{"tag":"Datatype","fields":[{"tyName":"Data"},[]]},{"tag":"Datatype","fields":[{"tyName":"Data"},[]]}]]}]]}]]]}]}},{"key":69,"value":{"tag":"ACompNode","fields":[[0,[{"tag":"Datatype","fields":[{"tyName":"Data"},[]]},{"tag":"Datatype","fields":[{"tyName":"List"},[{"tag":"Datatype","fields":[{"tyName":"Pair"},[{"tag":"Datatype","fields":[{"tyName":"Data"},[]]},{"tag":"Datatype","fields":[{"tyName":"Data"},[]]}]]}]]}]],{"tag":"Builtin1Internal","fields":[{"tag":"UnMapData"}]}]}},{"key":68,"value":{"tag":"AValNode","fields":[{"tag":"Datatype","fields":[{"tyName":"Data"},[]]},{"tag":"App","fields":[7,[{"tag":"AnId","fields":[67]}],[{"tag":"Nowhere"}],[0,[{"tag":"Datatype","fields":[{"tyName":"List"},[{"tag":"Datatype","fields":[{"tyName":"Data"},[]]}]]},{"tag":"Datatype","fields":[{"tyName":"Data"},[]]}]]]}]}},{"key":67,"value":{"tag":"AValNode","fields":[{"tag":"Datatype","fields":[{"tyName":"List"},[{"tag":"Datatype","fields":[{"tyName":"Data"},[]]}]]},{"tag":"App","fields":[4,[{"tag":"AnId","fields":[66]}],[{"tag":"Nowhere"}],[0,[{"tag":"Datatype","fields":[{"tyName":"List"},[{"tag":"Datatype","fields":[{"tyName":"Data"},[]]}]]},{"tag":"Datatype","fields":[{"tyName":"List"},[{"tag":"Datatype","fields":[{"tyName":"Data"},[]]}]]}]]]}]}},{"key":66,"value":{"tag":"AValNode","fields":[{"tag":"Datatype","fields":[{"tyName":"List"},[{"tag":"Datatype","fields":[{"tyName":"Data"},[]]}]]},{"tag":"App","fields":[2,[{"tag":"AnId","fields":[65]}],[{"tag":"Nowhere"},{"tag":"Nowhere"}],[0,[{"tag":"Datatype","fields":[{"tyName":"Pair"},[{"tag":"BuiltinFlat","fields":[{"tag":"IntegerT"}]},{"tag":"Datatype","fields":[{"tyName":"List"},[{"tag":"Datatype","fields":[{"tyName":"Data"},[]]}]]}]]},{"tag":"Datatype","fields":[{"tyName":"List"},[{"tag":"Datatype","fields":[{"tyName":"Data"},[]]}]]}]]]}]}},{"key":65,"value":{"tag":"AValNode","fields":[{"tag":"Datatype","fields":[{"tyName":"Pair"},[{"tag":"BuiltinFlat","fields":[{"tag":"IntegerT"}]},{"tag":"Datatype","fields":[{"tyName":"List"},[{"tag":"Datatype","fields":[{"tyName":"Data"},[]]}]]}]]},{"tag":"App","fields":[0,[{"tag":"AnId","fields":[57]}],[],[0,[{"tag":"Datatype","fields":[{"tyName":"Data"},[]]},{"tag":"Datatype","fields":[{"tyName":"Pair"},[{"tag":"BuiltinFlat","fields":[{"tag":"IntegerT"}]},{"tag":"Datatype","fields":[{"tyName":"List"},[{"tag":"Datatype","fields":[{"tyName":"Data"},[]]}]]}]]}]]]}]}},{"key":64,"value":{"tag":"AValNode","fields":[{"tag":"Datatype","fields":[{"tyName":"Data"},[]]},{"tag":"App","fields":[7,[{"tag":"AnId","fields":[33]}],[{"tag":"Nowhere"}],[0,[{"tag":"Datatype","fields":[{"tyName":"List"},[{"tag":"Datatype","fields":[{"tyName":"Data"},[]]}]]},{"tag":"Datatype","fields":[{"tyName":"Data"},[]]}]]]}]}},{"key":63,"value":{"tag":"AValNode","fields":[{"tag":"Datatype","fields":[{"tyName":"Data"},[]]},{"tag":"App","fields":[7,[{"tag":"AnId","fields":[32]}],[{"tag":"Nowhere"}],[0,[{"tag":"Datatype","fields":[{"tyName":"List"},[{"tag":"Datatype","fields":[{"tyName":"Data"},[]]}]]},{"tag":"Datatype","fields":[{"tyName":"Data"},[]]}]]]}]}},{"key":62,"value":{"tag":"AValNode","fields":[{"tag":"Datatype","fields":[{"tyName":"Data"},[]]},{"tag":"App","fields":[28,[{"tag":"AnId","fields":[21]},{"tag":"AnId","fields":[61]}],[],[0,[{"tag":"BuiltinFlat","fields":[{"tag":"IntegerT"}]},{"tag":"Datatype","fields":[{"tyName":"List"},[{"tag":"Datatype","fields":[{"tyName":"Data"},[]]}]]},{"tag":"Datatype","fields":[{"tyName":"Data"},[]]}]]]}]}},{"key":61,"value":{"tag":"AValNode","fields":[{"tag":"Datatype","fields":[{"tyName":"List"},[{"tag":"Datatype","fields":[{"tyName":"Data"},[]]}]]},{"tag":"App","fields":[25,[{"tag":"AnId","fields":[30]},{"tag":"AnId","fields":[60]}],[{"tag":"Nowhere"}],[0,[{"tag":"Datatype","fields":[{"tyName":"Data"},[]]},{"tag":"Datatype","fields":[{"tyName":"List"},[{"tag":"Datatype","fields":[{"tyName":"Data"},[]]}]]},{"tag":"Datatype","fields":[{"tyName":"List"},[{"tag":"Datatype","fields":[{"tyName":"Data"},[]]}]]}]]]}]}},{"key":60,"value":{"tag":"AValNode","fields":[{"tag":"Datatype","fields":[{"tyName":"List"},[{"tag":"Datatype","fields":[{"tyName":"Data"},[]]}]]},{"tag":"App","fields":[25,[{"tag":"AnId","fields":[59]},{"tag":"AnId","fields":[6]}],[{"tag":"Nowhere"}],[0,[{"tag":"Datatype","fields":[{"tyName":"Data"},[]]},{"tag":"Datatype","fields":[{"tyName":"List"},[{"tag":"Datatype","fields":[{"tyName":"Data"},[]]}]]},{"tag":"Datatype","fields":[{"tyName":"List"},[{"tag":"Datatype","fields":[{"tyName":"Data"},[]]}]]}]]]}]}},{"key":59,"value":{"tag":"AValNode","fields":[{"tag":"Datatype","fields":[{"tyName":"Data"},[]]},{"tag":"App","fields":[38,[{"tag":"AnId","fields":[58]}],[],[0,[{"tag":"Datatype","fields":[{"tyName":"List"},[{"tag":"Datatype","fields":[{"tyName":"Data"},[]]}]]},{"tag":"Datatype","fields":[{"tyName":"Data"},[]]}]]]}]}},{"key":58,"value":{"tag":"AValNode","fields":[{"tag":"Datatype","fields":[{"tyName":"List"},[{"tag":"Datatype","fields":[{"tyName":"Data"},[]]}]]},{"tag":"App","fields":[4,[{"tag":"AnId","fields":[56]}],[{"tag":"Nowhere"}],[0,[{"tag":"Datatype","fields":[{"tyName":"List"},[{"tag":"Datatype","fields":[{"tyName":"Data"},[]]}]]},{"tag":"Datatype","fields":[{"tyName":"List"},[{"tag":"Datatype","fields":[{"tyName":"Data"},[]]}]]}]]]}]}},{"key":57,"value":{"tag":"AValNode","fields":[{"tag":"Datatype","fields":[{"tyName":"Data"},[]]},{"tag":"App","fields":[7,[{"tag":"AnId","fields":[56]}],[{"tag":"Nowhere"}],[0,[{"tag":"Datatype","fields":[{"tyName":"List"},[{"tag":"Datatype","fields":[{"tyName":"Data"},[]]}]]},{"tag":"Datatype","fields":[{"tyName":"Data"},[]]}]]]}]}},{"key":56,"value":{"tag":"AValNode","fields":[{"tag":"Datatype","fields":[{"tyName":"List"},[{"tag":"Datatype","fields":[{"tyName":"Data"},[]]}]]},{"tag":"App","fields":[36,[{"tag":"AnId","fields":[55]}],[],[0,[{"tag":"Datatype","fields":[{"tyName":"Data"},[]]},{"tag":"Datatype","fields":[{"tyName":"List"},[{"tag":"Datatype","fields":[{"tyName":"Data"},[]]}]]}]]]}]}},{"key":55,"value":{"tag":"AValNode","fields":[{"tag":"Datatype","fields":[{"tyName":"Data"},[]]},{"tag":"App","fields":[7,[{"tag":"AnId","fields":[5]}],[{"tag":"Nowhere"}],[0,[{"tag":"Datatype","fields":[{"tyName":"List"},[{"tag":"Datatype","fields":[{"tyName":"Data"},[]]}]]},{"tag":"Datatype","fields":[{"tyName":"Data"},[]]}]]]}]}},{"key":54,"value":{"tag":"AValNode","fields":[{"tag":"ThunkT","fields":[[0,[{"tag":"Datatype","fields":[{"tyName":"Data"},[]]},{"tag":"Datatype","fields":[{"tyName":"Data"},[]]}]]]},{"tag":"Thunk","fields":[53]}]}},{"key":53,"value":{"tag":"ACompNode","fields":[[0,[{"tag":"Datatype","fields":[{"tyName":"Data"},[]]},{"tag":"Datatype","fields":[{"tyName":"Data"},[]]}]],{"tag":"LamInternal","fields":[{"tag":"AnId","fields":[52]}]}]}},{"key":52,"value":{"tag":"AValNode","fields":[{"tag":"Datatype","fields":[{"tyName":"Data"},[]]},{"tag":"App","fields":[51,[{"tag":"AnId","fields":[21]}],[],[0,[{"tag":"BuiltinFlat","fields":[{"tag":"IntegerT"}]},{"tag":"Datatype","fields":[{"tyName":"Data"},[]]}]]]}]}},{"key":51,"value":{"tag":"ACompNode","fields":[[0,[{"tag":"BuiltinFlat","fields":[{"tag":"IntegerT"}]},{"tag":"Datatype","fields":[{"tyName":"Data"},[]]}]],{"tag":"Builtin1Internal","fields":[{"tag":"IData"}]}]}},{"key":50,"value":{"tag":"AValNode","fields":[{"tag":"BuiltinFlat","fields":[{"tag":"BoolT"}]},{"tag":"App","fields":[43,[{"tag":"AnId","fields":[49]}],[{"tag":"Nowhere"}],[0,[{"tag":"Datatype","fields":[{"tyName":"List"},[{"tag":"Datatype","fields":[{"tyName":"Data"},[]]}]]},{"tag":"BuiltinFlat","fields":[{"tag":"BoolT"}]}]]]}]}},{"key":49,"value":{"tag":"AValNode","fields":[{"tag":"Datatype","fields":[{"tyName":"List"},[{"tag":"Datatype","fields":[{"tyName":"Data"},[]]}]]},{"tag":"App","fields":[36,[{"tag":"AnId","fields":[48]}],[],[0,[{"tag":"Datatype","fields":[{"tyName":"Data"},[]]},{"tag":"Datatype","fields":[{"tyName":"List"},[{"tag":"Datatype","fields":[{"tyName":"Data"},[]]}]]}]]]}]}},{"key":48,"value":{"tag":"AValNode","fields":[{"tag":"Datatype","fields":[{"tyName":"Data"},[]]},{"tag":"App","fields":[7,[{"tag":"AnId","fields":[47]}],[{"tag":"Nowhere"}],[0,[{"tag":"Datatype","fields":[{"tyName":"List"},[{"tag":"Datatype","fields":[{"tyName":"Data"},[]]}]]},{"tag":"Datatype","fields":[{"tyName":"Data"},[]]}]]]}]}},{"key":47,"value":{"tag":"AValNode","fields":[{"tag":"Datatype","fields":[{"tyName":"List"},[{"tag":"Datatype","fields":[{"tyName":"Data"},[]]}]]},{"tag":"App","fields":[4,[{"tag":"AnId","fields":[46]}],[{"tag":"Nowhere"}],[0,[{"tag":"Datatype","fields":[{"tyName":"List"},[{"tag":"Datatype","fields":[{"tyName":"Data"},[]]}]]},{"tag":"Datatype","fields":[{"tyName":"List"},[{"tag":"Datatype","fields":[{"tyName":"Data"},[]]}]]}]]]}]}},{"key":46,"value":{"tag":"AValNode","fields":[{"tag":"Datatype","fields":[{"tyName":"List"},[{"tag":"Datatype","fields":[{"tyName":"Data"},[]]}]]},{"tag":"App","fields":[2,[{"tag":"AnId","fields":[45]}],[{"tag":"Nowhere"},{"tag":"Nowhere"}],[0,[{"tag":"Datatype","fields":[{"tyName":"Pair"},[{"tag":"BuiltinFlat","fields":[{"tag":"IntegerT"}]},{"tag":"Datatype","fields":[{"tyName":"List"},[{"tag":"Datatype","fields":[{"tyName":"Data"},[]]}]]}]]},{"tag":"Datatype","fields":[{"tyName":"List"},[{"tag":"Datatype","fields":[{"tyName":"Data"},[]]}]]}]]]}]}},{"key":45,"value":{"tag":"AValNode","fields":[{"tag":"Datatype","fields":[{"tyName":"Pair"},[{"tag":"BuiltinFlat","fields":[{"tag":"IntegerT"}]},{"tag":"Datatype","fields":[{"tyName":"List"},[{"tag":"Datatype","fields":[{"tyName":"Data"},[]]}]]}]]},{"tag":"App","fields":[0,[{"tag":"AnId","fields":[42]}],[],[0,[{"tag":"Datatype","fields":[{"tyName":"Data"},[]]},{"tag":"Datatype","fields":[{"tyName":"Pair"},[{"tag":"BuiltinFlat","fields":[{"tag":"IntegerT"}]},{"tag":"Datatype","fields":[{"tyName":"List"},[{"tag":"Datatype","fields":[{"tyName":"Data"},[]]}]]}]]}]]]}]}},{"key":44,"value":{"tag":"ACompNode","fields":[[1,[{"tag":"BuiltinFlat","fields":[{"tag":"BoolT"}]},{"tag":"Abstraction","fields":[[0,0]]},{"tag":"Abstraction","fields":[[0,0]]},{"tag":"Abstraction","fields":[[0,0]]}]],{"tag":"Builtin3Internal","fields":[{"tag":"IfThenElse"}]}]}},{"key":43,"value":{"tag":"ACompNode","fields":[[1,[{"tag":"Datatype","fields":[{"tyName":"List"},[{"tag":"Abstraction","fields":[[0,0]]}]]},{"tag":"BuiltinFlat","fields":[{"tag":"BoolT"}]}]],{"tag":"Builtin1Internal","fields":[{"tag":"NullList"}]}]}},{"key":42,"value":{"tag":"AValNode","fields":[{"tag":"Datatype","fields":[{"tyName":"Data"},[]]},{"tag":"App","fields":[28,[{"tag":"AnId","fields":[21]},{"tag":"AnId","fields":[41]}],[],[0,[{"tag":"BuiltinFlat","fields":[{"tag":"IntegerT"}]},{"tag":"Datatype","fields":[{"tyName":"List"},[{"tag":"Datatype","fields":[{"tyName":"Data"},[]]}]]},{"tag":"Datatype","fields":[{"tyName":"Data"},[]]}]]]}]}},{"key":41,"value":{"tag":"AValNode","fields":[{"tag":"Datatype","fields":[{"tyName":"List"},[{"tag":"Datatype","fields":[{"tyName":"Data"},[]]}]]},{"tag":"App","fields":[25,[{"tag":"AnId","fields":[29]},{"tag":"AnId","fields":[40]}],[{"tag":"Nowhere"}],[0,[{"tag":"Datatype","fields":[{"tyName":"Data"},[]]},{"tag":"Datatype","fields":[{"tyName":"List"},[{"tag":"Datatype","fields":[{"tyName":"Data"},[]]}]]},{"tag":"Datatype","fields":[{"tyName":"List"},[{"tag":"Datatype","fields":[{"tyName":"Data"},[]]}]]}]]]}]}},{"key":40,"value":{"tag":"AValNode","fields":[{"tag":"Datatype","fields":[{"tyName":"List"},[{"tag":"Datatype","fields":[{"tyName":"Data"},[]]}]]},{"tag":"App","fields":[25,[{"tag":"AnId","fields":[39]},{"tag":"AnId","fields":[24]}],[{"tag":"Nowhere"}],[0,[{"tag":"Datatype","fields":[{"tyName":"Data"},[]]},{"tag":"Datatype","fields":[{"tyName":"List"},[{"tag":"Datatype","fields":[{"tyName":"Data"},[]]}]]},{"tag":"Datatype","fields":[{"tyName":"List"},[{"tag":"Datatype","fields":[{"tyName":"Data"},[]]}]]}]]]}]}},{"key":39,"value":{"tag":"AValNode","fields":[{"tag":"Datatype","fields":[{"tyName":"Data"},[]]},{"tag":"App","fields":[38,[{"tag":"AnId","fields":[37]}],[],[0,[{"tag":"Datatype","fields":[{"tyName":"List"},[{"tag":"Datatype","fields":[{"tyName":"Data"},[]]}]]},{"tag":"Datatype","fields":[{"tyName":"Data"},[]]}]]]}]}},{"key":38,"value":{"tag":"ACompNode","fields":[[0,[{"tag":"Datatype","fields":[{"tyName":"List"},[{"tag":"Datatype","fields":[{"tyName":"Data"},[]]}]]},{"tag":"Datatype","fields":[{"tyName":"Data"},[]]}]],{"tag":"Builtin1Internal","fields":[{"tag":"ListData"}]}]}},{"key":37,"value":{"tag":"AValNode","fields":[{"tag":"Datatype","fields":[{"tyName":"List"},[{"tag":"Datatype","fields":[{"tyName":"Data"},[]]}]]},{"tag":"App","fields":[36,[{"tag":"AnId","fields":[35]}],[],[0,[{"tag":"Datatype","fields":[{"tyName":"Data"},[]]},{"tag":"Datatype","fields":[{"tyName":"List"},[{"tag":"Datatype","fields":[{"tyName":"Data"},[]]}]]}]]]}]}},{"key":36,"value":{"tag":"ACompNode","fields":[[0,[{"tag":"Datatype","fields":[{"tyName":"Data"},[]]},{"tag":"Datatype","fields":[{"tyName":"List"},[{"tag":"Datatype","fields":[{"tyName":"Data"},[]]}]]}]],{"tag":"Builtin1Internal","fields":[{"tag":"UnListData"}]}]}},{"key":35,"value":{"tag":"AValNode","fields":[{"tag":"Datatype","fields":[{"tyName":"Data"},[]]},{"tag":"App","fields":[7,[{"tag":"AnId","fields":[34]}],[{"tag":"Nowhere"}],[0,[{"tag":"Datatype","fields":[{"tyName":"List"},[{"tag":"Datatype","fields":[{"tyName":"Data"},[]]}]]},{"tag":"Datatype","fields":[{"tyName":"Data"},[]]}]]]}]}},{"key":34,"value":{"tag":"AValNode","fields":[{"tag":"Datatype","fields":[{"tyName":"List"},[{"tag":"Datatype","fields":[{"tyName":"Data"},[]]}]]},{"tag":"App","fields":[4,[{"tag":"AnId","fields":[33]}],[{"tag":"Nowhere"}],[0,[{"tag":"Datatype","fields":[{"tyName":"List"},[{"tag":"Datatype","fields":[{"tyName":"Data"},[]]}]]},{"tag":"Datatype","fields":[{"tyName":"List"},[{"tag":"Datatype","fields":[{"tyName":"Data"},[]]}]]}]]]}]}},{"key":33,"value":{"tag":"AValNode","fields":[{"tag":"Datatype","fields":[{"tyName":"List"},[{"tag":"Datatype","fields":[{"tyName":"Data"},[]]}]]},{"tag":"App","fields":[4,[{"tag":"AnId","fields":[32]}],[{"tag":"Nowhere"}],[0,[{"tag":"Datatype","fields":[{"tyName":"List"},[{"tag":"Datatype","fields":[{"tyName":"Data"},[]]}]]},{"tag":"Datatype","fields":[{"tyName":"List"},[{"tag":"Datatype","fields":[{"tyName":"Data"},[]]}]]}]]]}]}},{"key":32,"value":{"tag":"AValNode","fields":[{"tag":"Datatype","fields":[{"tyName":"List"},[{"tag":"Datatype","fields":[{"tyName":"Data"},[]]}]]},{"tag":"App","fields":[2,[{"tag":"AnId","fields":[31]}],[{"tag":"Nowhere"},{"tag":"Nowhere"}],[0,[{"tag":"Datatype","fields":[{"tyName":"Pair"},[{"tag":"BuiltinFlat","fields":[{"tag":"IntegerT"}]},{"tag":"Datatype","fields":[{"tyName":"List"},[{"tag":"Datatype","fields":[{"tyName":"Data"},[]]}]]}]]},{"tag":"Datatype","fields":[{"tyName":"List"},[{"tag":"Datatype","fields":[{"tyName":"Data"},[]]}]]}]]]}]}},{"key":31,"value":{"tag":"AValNode","fields":[{"tag":"Datatype","fields":[{"tyName":"Pair"},[{"tag":"BuiltinFlat","fields":[{"tag":"IntegerT"}]},{"tag":"Datatype","fields":[{"tyName":"List"},[{"tag":"Datatype","fields":[{"tyName":"Data"},[]]}]]}]]},{"tag":"App","fields":[0,[{"tag":"AnId","fields":[30]}],[],[0,[{"tag":"Datatype","fields":[{"tyName":"Data"},[]]},{"tag":"Datatype","fields":[{"tyName":"Pair"},[{"tag":"BuiltinFlat","fields":[{"tag":"IntegerT"}]},{"tag":"Datatype","fields":[{"tyName":"List"},[{"tag":"Datatype","fields":[{"tyName":"Data"},[]]}]]}]]}]]]}]}},{"key":30,"value":{"tag":"AValNode","fields":[{"tag":"Datatype","fields":[{"tyName":"Data"},[]]},{"tag":"App","fields":[7,[{"tag":"AnId","fields":[3]}],[{"tag":"Nowhere"}],[0,[{"tag":"Datatype","fields":[{"tyName":"List"},[{"tag":"Datatype","fields":[{"tyName":"Data"},[]]}]]},{"tag":"Datatype","fields":[{"tyName":"Data"},[]]}]]]}]}},{"key":29,"value":{"tag":"AValNode","fields":[{"tag":"Datatype","fields":[{"tyName":"Data"},[]]},{"tag":"App","fields":[28,[{"tag":"AnId","fields":[21]},{"tag":"AnId","fields":[27]}],[],[0,[{"tag":"BuiltinFlat","fields":[{"tag":"IntegerT"}]},{"tag":"Datatype","fields":[{"tyName":"List"},[{"tag":"Datatype","fields":[{"tyName":"Data"},[]]}]]},{"tag":"Datatype","fields":[{"tyName":"Data"},[]]}]]]}]}},{"key":28,"value":{"tag":"ACompNode","fields":[[0,[{"tag":"BuiltinFlat","fields":[{"tag":"IntegerT"}]},{"tag":"Datatype","fields":[{"tyName":"List"},[{"tag":"Datatype","fields":[{"tyName":"Data"},[]]}]]},{"tag":"Datatype","fields":[{"tyName":"Data"},[]]}]],{"tag":"Builtin2Internal","fields":[{"tag":"ConstrData"}]}]}},{"key":27,"value":{"tag":"AValNode","fields":[{"tag":"Datatype","fields":[{"tyName":"List"},[{"tag":"Datatype","fields":[{"tyName":"Data"},[]]}]]},{"tag":"App","fields":[25,[{"tag":"AnId","fields":[18]},{"tag":"AnId","fields":[26]}],[{"tag":"Nowhere"}],[0,[{"tag":"Datatype","fields":[{"tyName":"Data"},[]]},{"tag":"Datatype","fields":[{"tyName":"List"},[{"tag":"Datatype","fields":[{"tyName":"Data"},[]]}]]},{"tag":"Datatype","fields":[{"tyName":"List"},[{"tag":"Datatype","fields":[{"tyName":"Data"},[]]}]]}]]]}]}},{"key":26,"value":{"tag":"AValNode","fields":[{"tag":"Datatype","fields":[{"tyName":"List"},[{"tag":"Datatype","fields":[{"tyName":"Data"},[]]}]]},{"tag":"App","fields":[25,[{"tag":"AnId","fields":[20]},{"tag":"AnId","fields":[24]}],[{"tag":"Nowhere"}],[0,[{"tag":"Datatype","fields":[{"tyName":"Data"},[]]},{"tag":"Datatype","fields":[{"tyName":"List"},[{"tag":"Datatype","fields":[{"tyName":"Data"},[]]}]]},{"tag":"Datatype","fields":[{"tyName":"List"},[{"tag":"Datatype","fields":[{"tyName":"Data"},[]]}]]}]]]}]}},{"key":25,"value":{"tag":"ACompNode","fields":[[1,[{"tag":"Abstraction","fields":[[0,0]]},{"tag":"Datatype","fields":[{"tyName":"List"},[{"tag":"Abstraction","fields":[[0,0]]}]]},{"tag":"Datatype","fields":[{"tyName":"List"},[{"tag":"Abstraction","fields":[[0,0]]}]]}]],{"tag":"Builtin2Internal","fields":[{"tag":"MkCons"}]}]}},{"key":24,"value":{"tag":"AValNode","fields":[{"tag":"Datatype","fields":[{"tyName":"List"},[{"tag":"Datatype","fields":[{"tyName":"Data"},[]]}]]},{"tag":"App","fields":[23,[],[{"tag":"There","fields":[{"tag":"Datatype","fields":[{"tyName":"Data"},[]]}]}],[0,[{"tag":"Datatype","fields":[{"tyName":"List"},[{"tag":"Datatype","fields":[{"tyName":"Data"},[]]}]]}]]]}]}},{"key":23,"value":{"tag":"ACompNode","fields":[[1,[{"tag":"Datatype","fields":[{"tyName":"List"},[{"tag":"Abstraction","fields":[[0,0]]}]]}]],{"tag":"ForceInternal","fields":[{"tag":"AnId","fields":[22]}]}]}},{"key":22,"value":{"tag":"AValNode","fields":[{"tag":"ThunkT","fields":[[1,[{"tag":"Datatype","fields":[{"tyName":"List"},[{"tag":"Abstraction","fields":[[0,0]]}]]}]]]},{"tag":"DataConstructor","fields":[{"tyName":"List"},"Nil",[]]}]}},{"key":21,"value":{"tag":"AValNode","fields":[{"tag":"BuiltinFlat","fields":[{"tag":"IntegerT"}]},{"tag":"Lit","fields":[{"tag":"AnInteger","fields":[0]}]}]}},{"key":20,"value":{"tag":"AValNode","fields":[{"tag":"Datatype","fields":[{"tyName":"Data"},[]]},{"tag":"App","fields":[7,[{"tag":"AnId","fields":[19]}],[{"tag":"Nowhere"}],[0,[{"tag":"Datatype","fields":[{"tyName":"List"},[{"tag":"Datatype","fields":[{"tyName":"Data"},[]]}]]},{"tag":"Datatype","fields":[{"tyName":"Data"},[]]}]]]}]}},{"key":19,"value":{"tag":"AValNode","fields":[{"tag":"Datatype","fields":[{"tyName":"List"},[{"tag":"Datatype","fields":[{"tyName":"Data"},[]]}]]},{"tag":"App","fields":[4,[{"tag":"AnId","fields":[17]}],[{"tag":"Nowhere"}],[0,[{"tag":"Datatype","fields":[{"tyName":"List"},[{"tag":"Datatype","fields":[{"tyName":"Data"},[]]}]]},{"tag":"Datatype","fields":[{"tyName":"List"},[{"tag":"Datatype","fields":[{"tyName":"Data"},[]]}]]}]]]}]}},{"key":18,"value":{"tag":"AValNode","fields":[{"tag":"Datatype","fields":[{"tyName":"Data"},[]]},{"tag":"App","fields":[7,[{"tag":"AnId","fields":[17]}],[{"tag":"Nowhere"}],[0,[{"tag":"Datatype","fields":[{"tyName":"List"},[{"tag":"Datatype","fields":[{"tyName":"Data"},[]]}]]},{"tag":"Datatype","fields":[{"tyName":"Data"},[]]}]]]}]}},{"key":17,"value":{"tag":"AValNode","fields":[{"tag":"Datatype","fields":[{"tyName":"List"},[{"tag":"Datatype","fields":[{"tyName":"Data"},[]]}]]},{"tag":"App","fields":[2,[{"tag":"AnId","fields":[16]}],[{"tag":"Nowhere"},{"tag":"Nowhere"}],[0,[{"tag":"Datatype","fields":[{"tyName":"Pair"},[{"tag":"BuiltinFlat","fields":[{"tag":"IntegerT"}]},{"tag":"Datatype","fields":[{"tyName":"List"},[{"tag":"Datatype","fields":[{"tyName":"Data"},[]]}]]}]]},{"tag":"Datatype","fields":[{"tyName":"List"},[{"tag":"Datatype","fields":[{"tyName":"Data"},[]]}]]}]]]}]}},{"key":16,"value":{"tag":"AValNode","fields":[{"tag":"Datatype","fields":[{"tyName":"Pair"},[{"tag":"BuiltinFlat","fields":[{"tag":"IntegerT"}]},{"tag":"Datatype","fields":[{"tyName":"List"},[{"tag":"Datatype","fields":[{"tyName":"Data"},[]]}]]}]]},{"tag":"App","fields":[0,[{"tag":"AnId","fields":[15]}],[],[0,[{"tag":"Datatype","fields":[{"tyName":"Data"},[]]},{"tag":"Datatype","fields":[{"tyName":"Pair"},[{"tag":"BuiltinFlat","fields":[{"tag":"IntegerT"}]},{"tag":"Datatype","fields":[{"tyName":"List"},[{"tag":"Datatype","fields":[{"tyName":"Data"},[]]}]]}]]}]]]}]}},{"key":15,"value":{"tag":"AValNode","fields":[{"tag":"Datatype","fields":[{"tyName":"Data"},[]]},{"tag":"App","fields":[7,[{"tag":"AnId","fields":[14]}],[{"tag":"Nowhere"}],[0,[{"tag":"Datatype","fields":[{"tyName":"List"},[{"tag":"Datatype","fields":[{"tyName":"Data"},[]]}]]},{"tag":"Datatype","fields":[{"tyName":"Data"},[]]}]]]}]}},{"key":14,"value":{"tag":"AValNode","fields":[{"tag":"Datatype","fields":[{"tyName":"List"},[{"tag":"Datatype","fields":[{"tyName":"Data"},[]]}]]},{"tag":"App","fields":[2,[{"tag":"AnId","fields":[13]}],[{"tag":"Nowhere"},{"tag":"Nowhere"}],[0,[{"tag":"Datatype","fields":[{"tyName":"Pair"},[{"tag":"BuiltinFlat","fields":[{"tag":"IntegerT"}]},{"tag":"Datatype","fields":[{"tyName":"List"},[{"tag":"Datatype","fields":[{"tyName":"Data"},[]]}]]}]]},{"tag":"Datatype","fields":[{"tyName":"List"},[{"tag":"Datatype","fields":[{"tyName":"Data"},[]]}]]}]]]}]}},{"key":13,"value":{"tag":"AValNode","fields":[{"tag":"Datatype","fields":[{"tyName":"Pair"},[{"tag":"BuiltinFlat","fields":[{"tag":"IntegerT"}]},{"tag":"Datatype","fields":[{"tyName":"List"},[{"tag":"Datatype","fields":[{"tyName":"Data"},[]]}]]}]]},{"tag":"App","fields":[0,[{"tag":"AnId","fields":[12]}],[],[0,[{"tag":"Datatype","fields":[{"tyName":"Data"},[]]},{"tag":"Datatype","fields":[{"tyName":"Pair"},[{"tag":"BuiltinFlat","fields":[{"tag":"IntegerT"}]},{"tag":"Datatype","fields":[{"tyName":"List"},[{"tag":"Datatype","fields":[{"tyName":"Data"},[]]}]]}]]}]]]}]}},{"key":12,"value":{"tag":"AValNode","fields":[{"tag":"Datatype","fields":[{"tyName":"Data"},[]]},{"tag":"App","fields":[7,[{"tag":"AnId","fields":[11]}],[{"tag":"Nowhere"}],[0,[{"tag":"Datatype","fields":[{"tyName":"List"},[{"tag":"Datatype","fields":[{"tyName":"Data"},[]]}]]},{"tag":"Datatype","fields":[{"tyName":"Data"},[]]}]]]}]}},{"key":11,"value":{"tag":"AValNode","fields":[{"tag":"Datatype","fields":[{"tyName":"List"},[{"tag":"Datatype","fields":[{"tyName":"Data"},[]]}]]},{"tag":"App","fields":[4,[{"tag":"AnId","fields":[10]}],[{"tag":"Nowhere"}],[0,[{"tag":"Datatype","fields":[{"tyName":"List"},[{"tag":"Datatype","fields":[{"tyName":"Data"},[]]}]]},{"tag":"Datatype","fields":[{"tyName":"List"},[{"tag":"Datatype","fields":[{"tyName":"Data"},[]]}]]}]]]}]}},{"key":10,"value":{"tag":"AValNode","fields":[{"tag":"Datatype","fields":[{"tyName":"List"},[{"tag":"Datatype","fields":[{"tyName":"Data"},[]]}]]},{"tag":"App","fields":[2,[{"tag":"AnId","fields":[9]}],[{"tag":"Nowhere"},{"tag":"Nowhere"}],[0,[{"tag":"Datatype","fields":[{"tyName":"Pair"},[{"tag":"BuiltinFlat","fields":[{"tag":"IntegerT"}]},{"tag":"Datatype","fields":[{"tyName":"List"},[{"tag":"Datatype","fields":[{"tyName":"Data"},[]]}]]}]]},{"tag":"Datatype","fields":[{"tyName":"List"},[{"tag":"Datatype","fields":[{"tyName":"Data"},[]]}]]}]]]}]}},{"key":9,"value":{"tag":"AValNode","fields":[{"tag":"Datatype","fields":[{"tyName":"Pair"},[{"tag":"BuiltinFlat","fields":[{"tag":"IntegerT"}]},{"tag":"Datatype","fields":[{"tyName":"List"},[{"tag":"Datatype","fields":[{"tyName":"Data"},[]]}]]}]]},{"tag":"App","fields":[0,[{"tag":"AnId","fields":[8]}],[],[0,[{"tag":"Datatype","fields":[{"tyName":"Data"},[]]},{"tag":"Datatype","fields":[{"tyName":"Pair"},[{"tag":"BuiltinFlat","fields":[{"tag":"IntegerT"}]},{"tag":"Datatype","fields":[{"tyName":"List"},[{"tag":"Datatype","fields":[{"tyName":"Data"},[]]}]]}]]}]]]}]}},{"key":8,"value":{"tag":"AValNode","fields":[{"tag":"Datatype","fields":[{"tyName":"Data"},[]]},{"tag":"App","fields":[7,[{"tag":"AnId","fields":[6]}],[{"tag":"Nowhere"}],[0,[{"tag":"Datatype","fields":[{"tyName":"List"},[{"tag":"Datatype","fields":[{"tyName":"Data"},[]]}]]},{"tag":"Datatype","fields":[{"tyName":"Data"},[]]}]]]}]}},{"key":7,"value":{"tag":"ACompNode","fields":[[1,[{"tag":"Datatype","fields":[{"tyName":"List"},[{"tag":"Abstraction","fields":[[0,0]]}]]},{"tag":"Abstraction","fields":[[0,0]]}]],{"tag":"Builtin1Internal","fields":[{"tag":"HeadList"}]}]}},{"key":6,"value":{"tag":"AValNode","fields":[{"tag":"Datatype","fields":[{"tyName":"List"},[{"tag":"Datatype","fields":[{"tyName":"Data"},[]]}]]},{"tag":"App","fields":[4,[{"tag":"AnId","fields":[5]}],[{"tag":"Nowhere"}],[0,[{"tag":"Datatype","fields":[{"tyName":"List"},[{"tag":"Datatype","fields":[{"tyName":"Data"},[]]}]]},{"tag":"Datatype","fields":[{"tyName":"List"},[{"tag":"Datatype","fields":[{"tyName":"Data"},[]]}]]}]]]}]}},{"key":5,"value":{"tag":"AValNode","fields":[{"tag":"Datatype","fields":[{"tyName":"List"},[{"tag":"Datatype","fields":[{"tyName":"Data"},[]]}]]},{"tag":"App","fields":[4,[{"tag":"AnId","fields":[3]}],[{"tag":"Nowhere"}],[0,[{"tag":"Datatype","fields":[{"tyName":"List"},[{"tag":"Datatype","fields":[{"tyName":"Data"},[]]}]]},{"tag":"Datatype","fields":[{"tyName":"List"},[{"tag":"Datatype","fields":[{"tyName":"Data"},[]]}]]}]]]}]}},{"key":4,"value":{"tag":"ACompNode","fields":[[1,[{"tag":"Datatype","fields":[{"tyName":"List"},[{"tag":"Abstraction","fields":[[0,0]]}]]},{"tag":"Datatype","fields":[{"tyName":"List"},[{"tag":"Abstraction","fields":[[0,0]]}]]}]],{"tag":"Builtin1Internal","fields":[{"tag":"TailList"}]}]}},{"key":3,"value":{"tag":"AValNode","fields":[{"tag":"Datatype","fields":[{"tyName":"List"},[{"tag":"Datatype","fields":[{"tyName":"Data"},[]]}]]},{"tag":"App","fields":[2,[{"tag":"AnId","fields":[1]}],[{"tag":"Nowhere"},{"tag":"Nowhere"}],[0,[{"tag":"Datatype","fields":[{"tyName":"Pair"},[{"tag":"BuiltinFlat","fields":[{"tag":"IntegerT"}]},{"tag":"Datatype","fields":[{"tyName":"List"},[{"tag":"Datatype","fields":[{"tyName":"Data"},[]]}]]}]]},{"tag":"Datatype","fields":[{"tyName":"List"},[{"tag":"Datatype","fields":[{"tyName":"Data"},[]]}]]}]]]}]}},{"key":2,"value":{"tag":"ACompNode","fields":[[2,[{"tag":"Datatype","fields":[{"tyName":"Pair"},[{"tag":"Abstraction","fields":[[0,0]]},{"tag":"Abstraction","fields":[[0,1]]}]]},{"tag":"Abstraction","fields":[[0,1]]}]],{"tag":"Builtin1Internal","fields":[{"tag":"SndPair"}]}]}},{"key":1,"value":{"tag":"AValNode","fields":[{"tag":"Datatype","fields":[{"tyName":"Pair"},[{"tag":"BuiltinFlat","fields":[{"tag":"IntegerT"}]},{"tag":"Datatype","fields":[{"tyName":"List"},[{"tag":"Datatype","fields":[{"tyName":"Data"},[]]}]]}]]},{"tag":"App","fields":[0,[{"tag":"AnArg","fields":[{"argDeBruijn":0,"argIndex":0,"argType":{"tag":"Datatype","fields":[{"tyName":"Data"},[]]}}]}],[],[0,[{"tag":"Datatype","fields":[{"tyName":"Data"},[]]},{"tag":"Datatype","fields":[{"tyName":"Pair"},[{"tag":"BuiltinFlat","fields":[{"tag":"IntegerT"}]},{"tag":"Datatype","fields":[{"tyName":"List"},[{"tag":"Datatype","fields":[{"tyName":"Data"},[]]}]]}]]}]]]}]}},{"key":0,"value":{"tag":"ACompNode","fields":[[0,[{"tag":"Datatype","fields":[{"tyName":"Data"},[]]},{"tag":"Datatype","fields":[{"tyName":"Pair"},[{"tag":"BuiltinFlat","fields":[{"tag":"IntegerT"}]},{"tag":"Datatype","fields":[{"tyName":"List"},[{"tag":"Datatype","fields":[{"tyName":"Data"},[]]}]]}]]}]],{"tag":"Builtin1Internal","fields":[{"tag":"UnConstrData"}]}]}}],"version":{"major":1,"minor":0}}